[
  {
    "nomor_urut": 1,
    "foto": "https://infopemilu.kpu.go.id/dct/berkas-silon/calon/237825/pas_foto/1688132890_e3579b26-d666-4bc3-88bd-5168a487ce31.jpeg",
    "nama": "SUSIADI, S.I.P.",
    "jenis_kelamin": "L",
    "alamat_kabko": "BANGKA BARAT",
    "profile": {},
    "id_partai": 8,
    "kode_dapil": "190504"
  },
  {
    "nomor_urut": 2,
    "foto": "https://infopemilu.kpu.go.id/dct/berkas-silon/calon_unggah/32292/pas_foto/1905041305830001.png",
    "nama": "RAMLAN",
    "jenis_kelamin": "L",
    "alamat_kabko": "BANGKA BARAT",
    "profile": {},
    "id_partai": 8,
    "kode_dapil": "190504"
  },
  {
    "nomor_urut": 3,
    "foto": "https://infopemilu.kpu.go.id/dct/berkas-silon/calon/237831/pas_foto/1688218820_e597c0d0-ce51-4bd5-a44d-869f25bf0b6d.jpeg",
    "nama": "ANJELI WIJAYA",
    "jenis_kelamin": "P",
    "alamat_kabko": "BANGKA BARAT",
    "profile": {},
    "id_partai": 8,
    "kode_dapil": "190504"
  },
  {
    "nomor_urut": 4,
    "foto": "https://infopemilu.kpu.go.id/dct/berkas-silon/calon_unggah/32292/pas_foto/1905041208610001.png",
    "nama": "BASIMAN",
    "jenis_kelamin": "L",
    "alamat_kabko": "BANGKA BARAT",
    "profile": {},
    "id_partai": 8,
    "kode_dapil": "190504"
  },
  {
    "nomor_urut": 5,
    "foto": "https://infopemilu.kpu.go.id/dct/berkas-silon/calon/237829/pas_foto/1688132567_6d6fe75e-72f0-42bf-85bc-6f6481ece5e6.jpeg",
    "nama": "AZHAR BAIHAQI",
    "jenis_kelamin": "L",
    "alamat_kabko": "BANGKA BARAT",
    "profile": {},
    "id_partai": 8,
    "kode_dapil": "190504"
  },
  {
    "nomor_urut": 6,
    "foto": "https://infopemilu.kpu.go.id/dct/berkas-silon/calon/452625/pas_foto/1688806984_5e5c5c46-b01b-479b-830b-d149c01c084d.jpeg",
    "nama": "ZULPAH",
    "jenis_kelamin": "P",
    "alamat_kabko": "BANGKA BARAT",
    "profile": {},
    "id_partai": 8,
    "kode_dapil": "190504"
  },
  {
    "nomor_urut": 7,
    "foto": "https://infopemilu.kpu.go.id/dct/berkas-silon/calon/452593/pas_foto/1688801696_ec1634e4-96ae-4a97-89ef-424b5aac0761.jpeg",
    "nama": "DELGI PRATAMA ADE PUTRA",
    "jenis_kelamin": "L",
    "alamat_kabko": "BANGKA BARAT",
    "profile": {},
    "id_partai": 8,
    "kode_dapil": "190504"
  },
  {
    "nomor_urut": 8,
    "foto": "https://infopemilu.kpu.go.id/dct/berkas-silon/calon/453879/pas_foto/1688809327_1a1a4065-22fc-4125-b14b-5f364f0c398c.jpeg",
    "nama": "ANTI",
    "jenis_kelamin": "P",
    "alamat_kabko": "BANGKA BARAT",
    "profile": {},
    "id_partai": 8,
    "kode_dapil": "190504"
  },
  {
    "nomor_urut": 9,
    "foto": "https://infopemilu.kpu.go.id/dct/berkas-silon/calon/452657/pas_foto/1688803632_45d6e9bb-88d6-4602-9bd8-0f4071869508.jpeg",
    "nama": "SYAMSU SAIMI",
    "jenis_kelamin": "L",
    "alamat_kabko": "BANGKA BARAT",
    "profile": {},
    "id_partai": 8,
    "kode_dapil": "190504"
  },
  {
    "nomor_urut": 1,
    "foto": "https://infopemilu.kpu.go.id/dct/berkas-silon/calon/128049/pas_foto/1683774490_4488dbd5-6fe2-4482-b510-19b3e4616608.jpeg",
    "nama": "OKTORAZSARI",
    "jenis_kelamin": "L",
    "alamat_kabko": "BANGKA BARAT",
    "profile": {},
    "id_partai": 10,
    "kode_dapil": "190504"
  },
  {
    "nomor_urut": 2,
    "foto": "https://infopemilu.kpu.go.id/dct/berkas-silon/calon/128709/pas_foto/1683462671_6f402197-c36c-49f2-b3ee-3e6feb6eea17.jpeg",
    "nama": "ARDIANSYAH NUANSA ALAM",
    "jenis_kelamin": "L",
    "alamat_kabko": "BANGKA BARAT",
    "profile": {},
    "id_partai": 10,
    "kode_dapil": "190504"
  },
  {
    "nomor_urut": 3,
    "foto": "https://infopemilu.kpu.go.id/dct/berkas-silon/calon/439999/pas_foto/1688646200_54c49f1d-cb0f-475f-a61b-a969ebe062bd.jpeg",
    "nama": "YULITA",
    "jenis_kelamin": "P",
    "alamat_kabko": "BANGKA BARAT",
    "profile": {},
    "id_partai": 10,
    "kode_dapil": "190504"
  },
  {
    "nomor_urut": 4,
    "foto": "https://infopemilu.kpu.go.id/dct/berkas-silon/calon/259944/pas_foto/1683954200_356c4f8b-2b72-4f9a-83e0-14890622fa0a.jpeg",
    "nama": "SUDARTO",
    "jenis_kelamin": "L",
    "alamat_kabko": "BANGKA BARAT",
    "profile": {},
    "id_partai": 10,
    "kode_dapil": "190504"
  },
  {
    "nomor_urut": 5,
    "foto": "https://infopemilu.kpu.go.id/dct/berkas-silon/calon/129140/pas_foto/1683780486_d3342a4d-15e3-47db-adb8-111d9b23abcd.jpeg",
    "nama": "SUADI",
    "jenis_kelamin": "L",
    "alamat_kabko": "BANGKA BARAT",
    "profile": {},
    "id_partai": 10,
    "kode_dapil": "190504"
  },
  {
    "nomor_urut": 6,
    "foto": "https://infopemilu.kpu.go.id/dct/berkas-silon/calon/129827/pas_foto/1683780637_a3f06be2-3edf-44d2-92c0-c49ce7c92ef4.jpeg",
    "nama": "FRISKA NOVALISA, S.Sos",
    "jenis_kelamin": "P",
    "alamat_kabko": "BANGKA BARAT",
    "profile": {},
    "id_partai": 10,
    "kode_dapil": "190504"
  },
  {
    "nomor_urut": 7,
    "foto": "https://infopemilu.kpu.go.id/dct/berkas-silon/calon/261681/pas_foto/1683787288_53985818-0935-453b-a9f0-fe89ed32a322.jpeg",
    "nama": "META SAPUTRI, S.Pd.",
    "jenis_kelamin": "P",
    "alamat_kabko": "BANGKA BARAT",
    "profile": {},
    "id_partai": 10,
    "kode_dapil": "190504"
  },
  {
    "nomor_urut": 8,
    "foto": "https://infopemilu.kpu.go.id/dct/berkas-silon/calon/260374/pas_foto/1683788482_9b980120-2ea3-4a30-b760-050bdf9a5427.jpeg",
    "nama": "YUNI PUTRI UTAMI",
    "jenis_kelamin": "P",
    "alamat_kabko": "BANGKA BARAT",
    "profile": {},
    "id_partai": 10,
    "kode_dapil": "190504"
  },
  {
    "nomor_urut": 9,
    "foto": "https://infopemilu.kpu.go.id/dct/berkas-silon/calon/260709/pas_foto/1683787940_1d1e8d0c-0143-4272-a79a-c25558bbd9be.jpeg",
    "nama": "JHOSY RIFTENI ANGGESA, S.Sos.",
    "jenis_kelamin": "P",
    "alamat_kabko": "BANGKA BARAT",
    "profile": {},
    "id_partai": 10,
    "kode_dapil": "190504"
  },
  {
    "nomor_urut": 1,
    "foto": "https://infopemilu.kpu.go.id/dct/berkas-silon/calon/248870/pas_foto/1683747128_1c84d09c-765c-4f53-8061-0814863ca921.jpeg",
    "nama": "H. BADRI SYAMSU, S.E.",
    "jenis_kelamin": "L",
    "alamat_kabko": "BANGKA BARAT",
    "profile": {
      "id_calon_dpr": "be55e363f76b950c46eb210eca542a53ed393d182cba79fd8c8cda889f4972897138c5d8b5c54ffefc2977b1708126854d0cf46e199bfc09fb3a13743e4c860cvLL3qa9jgUZ8L6x53+Stn1i61wYks4arLhs5XxL3zTs=",
      "logo_partai": "berkas-sipol/parpol/profil/gambar_parpol/1656305039_LOGO%20PDI%20PERJUANGAN.png",
      "status_publikasi": "Bersedia"
    },
    "id_partai": 12,
    "kode_dapil": "190504"
  },
  {
    "nomor_urut": 2,
    "foto": "https://infopemilu.kpu.go.id/dct/berkas-silon/calon/248871/pas_foto/1683749694_79f8a74b-a990-4d67-ab8c-9175fded7fde.jpeg",
    "nama": "YULI SANDRA, S.Sos",
    "jenis_kelamin": "L",
    "alamat_kabko": "BANGKA BARAT",
    "profile": {
      "id_calon_dpr": "1f6a605d2c55ab654f885de3ff888deb95807f12474668a9500ba3bf4be8cb1d4b1b3111b4e1fca348794e697536285111a1c5c60d75a99d93bb806c1cc5b1be0fgK8++q1yTtpxzZd0K9bZn8WVSo3eOuVC+LlGFGcoo=",
      "logo_partai": "berkas-sipol/parpol/profil/gambar_parpol/1656305039_LOGO%20PDI%20PERJUANGAN.png",
      "status_publikasi": "Bersedia"
    },
    "id_partai": 12,
    "kode_dapil": "190504"
  },
  {
    "nomor_urut": 3,
    "foto": "https://infopemilu.kpu.go.id/dct/berkas-silon/calon/248872/pas_foto/1683748768_5a22dac0-48e1-47a1-b49f-5fabaeb52b76.jpeg",
    "nama": "DELLA SAFIRA SAFITRI",
    "jenis_kelamin": "P",
    "alamat_kabko": "BANGKA BARAT",
    "profile": {
      "id_calon_dpr": "38636109b0960dbff06483dd01c3984345b3228d66ec6b02e7800ebe835ed8a36606f0e3253816dd6541afbb674d2224d00063962b1f96125f0b12737f7ceb71WUsyXXjRxNb3bKJdGo3bN1IpQ58arJFDuDjKw4h/yJo=",
      "logo_partai": "berkas-sipol/parpol/profil/gambar_parpol/1656305039_LOGO%20PDI%20PERJUANGAN.png",
      "status_publikasi": "Bersedia"
    },
    "id_partai": 12,
    "kode_dapil": "190504"
  },
  {
    "nomor_urut": 4,
    "foto": "https://infopemilu.kpu.go.id/dct/berkas-silon/calon/248873/pas_foto/1683748609_f5c26fd8-2b36-4609-8eec-355384b4331c.jpeg",
    "nama": "YUSMIN, S.E.",
    "jenis_kelamin": "L",
    "alamat_kabko": "BANGKA BARAT",
    "profile": {
      "id_calon_dpr": "0ff87144ed240a179b264d71ab38d23e08ac1f958df99d658fd4e0bf94ce3ab68aa106e580872a6e19796e904cb47fe6897c710f6de755170a4e4164c0952868oXTgwNuT7bcaHLWhGZXDZQt5QYG0944i9sdZm5vNFFU=",
      "logo_partai": "berkas-sipol/parpol/profil/gambar_parpol/1656305039_LOGO%20PDI%20PERJUANGAN.png",
      "status_publikasi": "Bersedia"
    },
    "id_partai": 12,
    "kode_dapil": "190504"
  },
  {
    "nomor_urut": 5,
    "foto": "https://infopemilu.kpu.go.id/dct/berkas-silon/calon/248874/pas_foto/1683746920_8ea8b224-4da9-4048-8328-7ca0f4e8869a.jpeg",
    "nama": "G. HERMANSYAH",
    "jenis_kelamin": "L",
    "alamat_kabko": "BANGKA BARAT",
    "profile": {
      "id_calon_dpr": "a1be34815a659520d332ddbbd2d98bb6d34b34bd93b29a1cbb1d35e5a077010452e3a9b7c99fe93f3ee0c5ca789c52283e11d79317b020fc5ad8fcf099f45e6c8JWFMj4mWKEMMDlppEUHsNCcaI+2hr7/MMHQSLtKRDg=",
      "logo_partai": "berkas-sipol/parpol/profil/gambar_parpol/1656305039_LOGO%20PDI%20PERJUANGAN.png",
      "status_publikasi": "Bersedia"
    },
    "id_partai": 12,
    "kode_dapil": "190504"
  },
  {
    "nomor_urut": 6,
    "foto": "https://infopemilu.kpu.go.id/dct/berkas-silon/calon/248875/pas_foto/1683747982_da166cc2-fcf0-4589-acf7-aa0d8dcad6c7.jpeg",
    "nama": "WIWIT SINTA SURYANI, S.H.",
    "jenis_kelamin": "P",
    "alamat_kabko": "BANGKA BARAT",
    "profile": {
      "id_calon_dpr": "1ccf1b69df431183964de1f71bbd01f09fcc313efa79ff9002e6b0b6a6af1891c3aa94a0b63ee0695057bf06229651f449d6ff09cb789bd418846e4c3808a0adx1V0el86AX3fEYQxoaQoK8X6eOtQk8NgQyAfZeYCQB8=",
      "logo_partai": "berkas-sipol/parpol/profil/gambar_parpol/1656305039_LOGO%20PDI%20PERJUANGAN.png",
      "status_publikasi": "Bersedia"
    },
    "id_partai": 12,
    "kode_dapil": "190504"
  },
  {
    "nomor_urut": 7,
    "foto": "https://infopemilu.kpu.go.id/dct/berkas-silon/calon/248876/pas_foto/1683747803_f1739451-88e3-4616-9287-410418a705c2.jpeg",
    "nama": "KARTINA",
    "jenis_kelamin": "P",
    "alamat_kabko": "BANGKA BARAT",
    "profile": {
      "id_calon_dpr": "058b8889b852d9623b6954c3705f5071f65eda32faaedba19046532c2e1447dae9cf8986ee5d2f6e647b3cc32880d1d8d30eb7942f4b5f44b2fec29c4096f962hFtfi0TtcuBR8rVghWvhUARruXynRWnhPFHyBFs1Jcs=",
      "logo_partai": "berkas-sipol/parpol/profil/gambar_parpol/1656305039_LOGO%20PDI%20PERJUANGAN.png",
      "pilihan_publikasi": "datadiri,alamat,pekerjaan,penghargaan,motivasi,program",
      "status_publikasi": "Bersedia Sebagian"
    },
    "id_partai": 12,
    "kode_dapil": "190504"
  },
  {
    "nomor_urut": 8,
    "foto": "https://infopemilu.kpu.go.id/dct/berkas-silon/calon/248877/pas_foto/1683747413_a5cf785b-96bb-428d-8198-b36a8300d25c.jpeg",
    "nama": "SARIPAH AINI",
    "jenis_kelamin": "P",
    "alamat_kabko": "BANGKA BARAT",
    "profile": {
      "id_calon_dpr": "0a802290f1eeb4936ee0e5825bb1cb236313d084d610ef75b66b194acbc9322adc11d145d329c24dcdbbc8332a39a1f611a6198d45d069138e3f9b04a5ad4a54iaeigyDK5Om5UTG3LDXSie/51sJmvPGWXc850qmq85A=",
      "logo_partai": "berkas-sipol/parpol/profil/gambar_parpol/1656305039_LOGO%20PDI%20PERJUANGAN.png",
      "status_publikasi": "Bersedia"
    },
    "id_partai": 12,
    "kode_dapil": "190504"
  },
  {
    "nomor_urut": 9,
    "foto": "https://infopemilu.kpu.go.id/dct/berkas-silon/calon/248878/pas_foto/1683747562_4a985d63-6bca-4411-8853-f56d27d7a977.jpeg",
    "nama": "BUJANG FAHROZI",
    "jenis_kelamin": "L",
    "alamat_kabko": "BANGKA BARAT",
    "profile": {},
    "id_partai": 12,
    "kode_dapil": "190504"
  },
  {
    "nomor_urut": 1,
    "foto": "https://infopemilu.kpu.go.id/dct/berkas-silon/calon/243380/pas_foto/1683741326_1adcdb53-0478-4962-8e08-e442a56136d4.jpeg",
    "nama": "MEDI HESTRI, S.Ag",
    "jenis_kelamin": "L",
    "alamat_kabko": "BANGKA BARAT",
    "profile": {
      "id_calon_dpr": "b1b51f485f10cf7e4d98a0e7ff5ca2492765ac616715b9518c6069f8f2a4c460f749a722c2691e6df06a841979eef2df3d78bf0e9ca607f627f8e3dfa7314e5auXyYv4IOGSxNtrTaa2WfZNWtznZ/PErV/s6U3TxgYvQ=",
      "logo_partai": "berkas-sipol/parpol/profil/gambar_parpol/1656586681_Logo%20Golkar.png",
      "status_publikasi": "Bersedia"
    },
    "id_partai": 9,
    "kode_dapil": "190504"
  },
  {
    "nomor_urut": 2,
    "foto": "https://infopemilu.kpu.go.id/dct/berkas-silon/calon/244885/pas_foto/1688825497_a8f97ded-6470-40f0-9bd6-dcbf7c37d951.jpeg",
    "nama": "PATRIS LUMUMBA, S.H.",
    "jenis_kelamin": "L",
    "alamat_kabko": "KOTA PANGKAL PINANG",
    "profile": {
      "id_calon_dpr": "9b495a07585dfb728ee1f937eece874b27edf824e432920363bb9d3f68f280c956556dc65eb12ae5745acc586f96d47e8e9b0025b58f51e19f904cde051b71d4s1vH+q8vTC1TQALsp536S9e9k7g1EUVL+MJ8IHLGZ0U=",
      "logo_partai": "berkas-sipol/parpol/profil/gambar_parpol/1656586681_Logo%20Golkar.png",
      "status_publikasi": "Bersedia"
    },
    "id_partai": 9,
    "kode_dapil": "190504"
  },
  {
    "nomor_urut": 3,
    "foto": "https://infopemilu.kpu.go.id/dct/berkas-silon/calon/245684/pas_foto/1683742354_9f2337a2-2289-4fa5-9ec6-4f3fae323e5b.jpeg",
    "nama": "NOLA, S.E.",
    "jenis_kelamin": "P",
    "alamat_kabko": "KOTA BEKASI",
    "profile": {
      "id_calon_dpr": "a7b340b1f59ab0636bfe7b490150374b98033d892f9891754247280ff8abe3a78e120c4fb82c167e6874241a66d10984b2264d9427ce7b650725dbe90396d0197pyiqDo5yxa2RCtqW8aTTjhs26ATrSrcmWQm/q+5+54=",
      "logo_partai": "berkas-sipol/parpol/profil/gambar_parpol/1656586681_Logo%20Golkar.png",
      "status_publikasi": "Bersedia"
    },
    "id_partai": 9,
    "kode_dapil": "190504"
  },
  {
    "nomor_urut": 4,
    "foto": "https://infopemilu.kpu.go.id/dct/berkas-silon/calon/246229/pas_foto/1683743238_79ee926a-9c8b-488a-9167-e3cf5614c5a3.jpeg",
    "nama": "SEPTIADI, S.T.",
    "jenis_kelamin": "L",
    "alamat_kabko": "BANGKA BARAT",
    "profile": {
      "id_calon_dpr": "7b8e92e26522dc490da7a47c61ce8c5fc868eed3df599a03b502eb326d767054a45faa56e443afc0088947e8005d23988994023d5b5c51f56bbe280615896f0bfALLV1rd8z0sRRro1Fmri98GOHXpx3u2DNs9lVk12JE=",
      "logo_partai": "berkas-sipol/parpol/profil/gambar_parpol/1656586681_Logo%20Golkar.png",
      "status_publikasi": "Bersedia"
    },
    "id_partai": 9,
    "kode_dapil": "190504"
  },
  {
    "nomor_urut": 5,
    "foto": "https://infopemilu.kpu.go.id/dct/berkas-silon/calon/246481/pas_foto/1683743725_d2e21aaa-10bd-417f-902a-c3796b221f4c.jpeg",
    "nama": "RIDWAN, S.H.",
    "jenis_kelamin": "L",
    "alamat_kabko": "BANGKA BARAT",
    "profile": {
      "id_calon_dpr": "f6e02470590194d29594d56b683dc80acae5c942ade55861809cb8968b1f3b39ef6cd506e51a1db25ef0fb044d17ac2a389708350b5e05602b63d589c4bb82bcMAzt7+kNNYRMhyouV9IFSYRNgRXzsi1XLVRLIWLuR4U=",
      "logo_partai": "berkas-sipol/parpol/profil/gambar_parpol/1656586681_Logo%20Golkar.png",
      "status_publikasi": "Bersedia"
    },
    "id_partai": 9,
    "kode_dapil": "190504"
  },
  {
    "nomor_urut": 6,
    "foto": "https://infopemilu.kpu.go.id/dct/berkas-silon/calon/247330/pas_foto/1683744728_9466d22f-a038-4192-a00b-7a1991d27ded.jpeg",
    "nama": "ROSMINI",
    "jenis_kelamin": "P",
    "alamat_kabko": "BANGKA BARAT",
    "profile": {
      "id_calon_dpr": "a0d2e34460e326fff9b752dbe1ea0eb146d9dddf976a37051dff68ef46fd16999845ec2771fb12f81b310e3049811ed95aba21415b45c6b745841611b3595af0TjkVQsA/TSG/4/wNbX32KQQoWeJJmaw5GOJT1odrANk=",
      "logo_partai": "berkas-sipol/parpol/profil/gambar_parpol/1656586681_Logo%20Golkar.png",
      "status_publikasi": "Bersedia"
    },
    "id_partai": 9,
    "kode_dapil": "190504"
  },
  {
    "nomor_urut": 7,
    "foto": "https://infopemilu.kpu.go.id/dct/berkas-silon/calon/248298/pas_foto/1688825626_33ae8e22-1a93-49fb-adf5-2d73138b1573.jpeg",
    "nama": "INDRA JAYA",
    "jenis_kelamin": "L",
    "alamat_kabko": "BANGKA BARAT",
    "profile": {
      "id_calon_dpr": "8f134c5bd7b9a2a80321bb5189ae768309058d2fff4b1567bfd3cc56d773ce7a3e8e4b66f4a7f0dcc1ef09b8bc0c55b3852316649439ab5e8216ee96acca47bdgDSjastujBX+Zp968hpuYp5lod9xN9QgJ3XlB508iTQ=",
      "logo_partai": "berkas-sipol/parpol/profil/gambar_parpol/1656586681_Logo%20Golkar.png",
      "status_publikasi": "Bersedia"
    },
    "id_partai": 9,
    "kode_dapil": "190504"
  },
  {
    "nomor_urut": 8,
    "foto": "https://infopemilu.kpu.go.id/dct/berkas-silon/calon/248776/pas_foto/1688825948_c02f2002-ddd3-47e0-b510-2c50f50d84a1.jpeg",
    "nama": "RUSDI",
    "jenis_kelamin": "L",
    "alamat_kabko": "BANGKA BARAT",
    "profile": {
      "id_calon_dpr": "1a6bed7714678bb0f4c4be9df31332a7466e7a1594331b1d5f1627af830dc2e67205055945453879493b00aec909e01bbc0eca36f9f00935db7156d586fe868eUtbrrXTWptTIzd79dK21qtwREgJIK4QWfcJ01dqaR7k=",
      "logo_partai": "berkas-sipol/parpol/profil/gambar_parpol/1656586681_Logo%20Golkar.png",
      "status_publikasi": "Bersedia"
    },
    "id_partai": 9,
    "kode_dapil": "190504"
  },
  {
    "nomor_urut": 9,
    "foto": "https://infopemilu.kpu.go.id/dct/berkas-silon/calon/249381/pas_foto/1688825537_abd1777c-5d93-490f-8bb6-41f9c27f2ced.jpeg",
    "nama": "MARRELLA, A.Md.Keb",
    "jenis_kelamin": "P",
    "alamat_kabko": "BANGKA",
    "profile": {
      "id_calon_dpr": "8d499afe1cccb571f5c48e3cd2b1a54ff9120023a87fffe88aacd616edba3aae0f24854746b3e6ad2e489845ae091918bd1e0f237de8880e35251daad5058af8TGgdF3giF0RD0w1H0eFaO+OqFTmgc5DWMart0lRfUfs=",
      "logo_partai": "berkas-sipol/parpol/profil/gambar_parpol/1656586681_Logo%20Golkar.png",
      "status_publikasi": "Bersedia"
    },
    "id_partai": 9,
    "kode_dapil": "190504"
  },
  {
    "nomor_urut": 1,
    "foto": "https://infopemilu.kpu.go.id/dct/berkas-silon/calon/19874/pas_foto/1683247034_7976fb45-6d10-4805-8a33-6bd9945660ea.jpeg",
    "nama": "MERIYANTI",
    "jenis_kelamin": "P",
    "alamat_kabko": "BANGKA BARAT",
    "profile": {
      "id_calon_dpr": "aab4df18ec43a0b52a3796837b68f45f57c152caf54a60272ca64a1e303a4d79e757e6c426cd21baf5867e2897692e506c14f22743087bb10b84860c934d862d4x6r/1eqxHKRDJpzohRrZ9I5Wy81qAlgYsHLmk66/lw=",
      "logo_partai": "berkas-sipol/parpol/profil/gambar_parpol/1656224727_Logo%20NasDem%20KPU.png",
      "status_publikasi": "Bersedia"
    },
    "id_partai": 4,
    "kode_dapil": "190504"
  },
  {
    "nomor_urut": 2,
    "foto": "https://infopemilu.kpu.go.id/dct/berkas-silon/calon/19972/pas_foto/1683244383_9aec8fc7-0d89-4dbb-baf4-3b5f81241197.jpeg",
    "nama": "KARMAN",
    "jenis_kelamin": "L",
    "alamat_kabko": "BANGKA BARAT",
    "profile": {
      "id_calon_dpr": "4f885a6919c9e858bf1f1e802158767c96119345082b156eeb3064221250d80edf81f628db20635db9b8b0cbb92ed3b4cc6479eb5abce764e3a77586c8f1e44cYWNvryJHZyAUAANB129P8rWf7BmWACShoKFwtSoLUXE=",
      "logo_partai": "berkas-sipol/parpol/profil/gambar_parpol/1656224727_Logo%20NasDem%20KPU.png",
      "status_publikasi": "Bersedia"
    },
    "id_partai": 4,
    "kode_dapil": "190504"
  },
  {
    "nomor_urut": 3,
    "foto": "https://infopemilu.kpu.go.id/dct/berkas-silon/calon/20019/pas_foto/1683232212_c0acfd94-6f54-45e1-ae99-f34684d2b33f.jpeg",
    "nama": "MARYONO",
    "jenis_kelamin": "L",
    "alamat_kabko": "BANGKA BARAT",
    "profile": {
      "id_calon_dpr": "f6ce0c063ec7927ff8b927c5bed7bcf3fda25265b3b516bf474fa0ea6fd1c17ea8455f7869f29513fa767058d81943abd43bc48bd4e4459e18b4d742e5fcb82f2krfvOSAw+eUgEt9YRg7Zo6VkDmMWCtEP7Rk1u3C530=",
      "logo_partai": "berkas-sipol/parpol/profil/gambar_parpol/1656224727_Logo%20NasDem%20KPU.png",
      "status_publikasi": "Bersedia"
    },
    "id_partai": 4,
    "kode_dapil": "190504"
  },
  {
    "nomor_urut": 4,
    "foto": "https://infopemilu.kpu.go.id/dct/berkas-silon/calon/20092/pas_foto/1683246310_c841612f-0401-4a0e-8b81-7b6e8b1757d0.jpeg",
    "nama": "MARYUDI, A.M.d",
    "jenis_kelamin": "L",
    "alamat_kabko": "BANGKA BARAT",
    "profile": {
      "id_calon_dpr": "20b362027b1dc30c8e726d48467f3e76ae28783dff93b6403eb01248689daa6bf455a622ae9486a6c58b87a531c97777636d409484f110d503389b009755c36f4PQ0ie6il1VBv9Jg6ECDhVeV/SDwhV3MX3ZpVm9tyyo=",
      "logo_partai": "berkas-sipol/parpol/profil/gambar_parpol/1656224727_Logo%20NasDem%20KPU.png",
      "status_publikasi": "Bersedia"
    },
    "id_partai": 4,
    "kode_dapil": "190504"
  },
  {
    "nomor_urut": 5,
    "foto": "https://infopemilu.kpu.go.id/dct/berkas-silon/calon/21041/pas_foto/1683243832_bb16b6a8-d436-43b9-b41e-27f4cca40307.jpeg",
    "nama": "NORAEMA",
    "jenis_kelamin": "P",
    "alamat_kabko": "BANGKA BARAT",
    "profile": {
      "id_calon_dpr": "fb95d8682f395c7535e9304040765d831e398332e4ab5aa5ce14e92e7e75b119c183dcb84b39cb51d39b70a076445a05a13233722f6ca4cbfb8ac38630982f1eOoXh12t3DDRhyvSp0dsvyrYwmLw+YYoI9s450lPaEpk=",
      "logo_partai": "berkas-sipol/parpol/profil/gambar_parpol/1656224727_Logo%20NasDem%20KPU.png",
      "status_publikasi": "Bersedia"
    },
    "id_partai": 4,
    "kode_dapil": "190504"
  },
  {
    "nomor_urut": 6,
    "foto": "https://infopemilu.kpu.go.id/dct/berkas-silon/calon/21130/pas_foto/1683268483_bdce94ca-bdb0-4c71-8715-bb5666375ef4.jpeg",
    "nama": "KASMIDIN, S.Pd.SD",
    "jenis_kelamin": "L",
    "alamat_kabko": "BANGKA BARAT",
    "profile": {
      "id_calon_dpr": "4a1b2fbb13f8a9441c54a58f32a78a883823380d3e1faaa0a737d73d63e05933746d1199d7f1a3b271a62c5c28942cb69f19fe65cee1300c583fb5e3cab68362GPSB6xl1gKfsMKDwrLEG71svzAvgsPSZiRN9nu2oK+A=",
      "logo_partai": "berkas-sipol/parpol/profil/gambar_parpol/1656224727_Logo%20NasDem%20KPU.png",
      "status_publikasi": "Bersedia"
    },
    "id_partai": 4,
    "kode_dapil": "190504"
  },
  {
    "nomor_urut": 7,
    "foto": "https://infopemilu.kpu.go.id/dct/berkas-silon/calon/21185/pas_foto/1683232034_08a8bec1-c7a9-4c90-bcae-3ce049ee8608.jpeg",
    "nama": "IWAN FIRDAUS, S.E.",
    "jenis_kelamin": "L",
    "alamat_kabko": "BANGKA BARAT",
    "profile": {
      "id_calon_dpr": "68285e5814c3f6bdead9f3388b87e150fc9e842374ec86f6ef04519257356c86b6148f03fd36ad07fdac5fa0f7e6e6fda0ca0465549d2c591bbc18ba6ad1f4caBw64A2YR+LFz/AGt2ncXmKAV/g1wdhI3HmkbThL/78s=",
      "logo_partai": "berkas-sipol/parpol/profil/gambar_parpol/1656224727_Logo%20NasDem%20KPU.png",
      "status_publikasi": "Bersedia"
    },
    "id_partai": 4,
    "kode_dapil": "190504"
  },
  {
    "nomor_urut": 8,
    "foto": "https://infopemilu.kpu.go.id/dct/berkas-silon/calon/21246/pas_foto/1683244461_489ee94d-aee7-44f4-9983-1d3b828bfbb5.jpeg",
    "nama": "DESY",
    "jenis_kelamin": "P",
    "alamat_kabko": "BANGKA BARAT",
    "profile": {
      "id_calon_dpr": "6f51be3b30036f69a6b5da29d5d356b9e1f29f1e0424d3ca4df15040316534001c1b1842b0e91fcc1d839eb06ea5b40c32a2549cc69d42f933aa32fe1908c75bc2poJOG3oEkXM4NPM6CUWXEsLd3Q6pxglDThXm8shG8=",
      "logo_partai": "berkas-sipol/parpol/profil/gambar_parpol/1656224727_Logo%20NasDem%20KPU.png",
      "status_publikasi": "Bersedia"
    },
    "id_partai": 4,
    "kode_dapil": "190504"
  },
  {
    "nomor_urut": 9,
    "foto": "https://infopemilu.kpu.go.id/dct/berkas-silon/calon/437298/pas_foto/1688717163_b7fe8bac-5401-4ad8-9cf1-7bd3a1d8e390.jpeg",
    "nama": "KAMILIAN",
    "jenis_kelamin": "L",
    "alamat_kabko": "BANGKA BARAT",
    "profile": {
      "id_calon_dpr": "0f016fd4474219d9f0589232b884aefacd8a36d4c6920ccbbcaaaa0b380c07b8a7f529e416ef221cb01b66fc2a9c990f3002a45565c31af18db1160fa64a49744r8+iXhYtLDVQok34BUyzkodTMRZl+5jth2g6atJHRs=",
      "logo_partai": "berkas-sipol/parpol/profil/gambar_parpol/1656224727_Logo%20NasDem%20KPU.png",
      "status_publikasi": "Bersedia"
    },
    "id_partai": 4,
    "kode_dapil": "190504"
  },
  {
    "nomor_urut": 1,
    "foto": "https://infopemilu.kpu.go.id/dct/berkas-silon/calon/406083/pas_foto/1684151706_a397b12b-1687-40ad-904a-d2bd4b50f717.jpeg",
    "nama": "ALINA",
    "jenis_kelamin": "P",
    "alamat_kabko": "BANGKA BARAT",
    "profile": {
      "id_calon_dpr": "f8e313fb8d1e385c6986dc8b8008b3788d3d2f763896409040de432b23dbc8ffa36aeb5e2596c1fdf0ab5a215bc4de61a68af66da7a4a4cf3c71c287eb9e9db6Ih4/wgtLe5qCLTVfXh+si0XNmlqptxowhYZ+p1P031Q=",
      "logo_partai": "berkas-sipol/parpol/profil/gambar_parpol/1658983159_Logo%20Gelora%20Portrait.png",
      "status_publikasi": "Bersedia"
    },
    "id_partai": 77,
    "kode_dapil": "190504"
  },
  {
    "nomor_urut": 2,
    "foto": "https://infopemilu.kpu.go.id/dct/berkas-silon/calon/406082/pas_foto/1684143704_b17d44bf-53eb-432f-9bbb-131be75ca655.jpeg",
    "nama": "IRPAN",
    "jenis_kelamin": "L",
    "alamat_kabko": "BANGKA BARAT",
    "profile": {
      "id_calon_dpr": "c19a5c2a1c4d24798b702ed6b1bf434ad264829dbf89ce80a3fb9ae112446f19a4bfe3f2e63aa7332145fdcac5de6e35553284a4523b4d1e1118a6bddaa906d2r8W7JOpyeU6rDP3ye21+6KpSdmHMZ3FZG6RmZerjrts=",
      "logo_partai": "berkas-sipol/parpol/profil/gambar_parpol/1658983159_Logo%20Gelora%20Portrait.png",
      "status_publikasi": "Bersedia"
    },
    "id_partai": 77,
    "kode_dapil": "190504"
  },
  {
    "nomor_urut": 3,
    "foto": "https://infopemilu.kpu.go.id/dct/berkas-silon/calon/406085/pas_foto/1684154950_a71fb4f4-13bb-4b98-a4e8-b5fc7be612ff.jpeg",
    "nama": "ELISA",
    "jenis_kelamin": "P",
    "alamat_kabko": "BANGKA BARAT",
    "profile": {
      "id_calon_dpr": "26e712e52aed83267093a7c00d5423e8ec5b36606cb5ce02daac8ef53b2b41a55b18151735971c4cf6a4ec10396a0f1c388dd95822a13049efb7e63215eb65a9G3aaIvDVqDfxhPfMJ0JViNopPr3R2l+BUg1/J2soWpo=",
      "logo_partai": "berkas-sipol/parpol/profil/gambar_parpol/1658983159_Logo%20Gelora%20Portrait.png",
      "status_publikasi": "Bersedia"
    },
    "id_partai": 77,
    "kode_dapil": "190504"
  },
  {
    "nomor_urut": 4,
    "foto": "https://infopemilu.kpu.go.id/dct/berkas-silon/calon/406084/pas_foto/1684154132_1a60e611-1edd-4049-b251-2e126be9d714.jpeg",
    "nama": "DIAN HARISTA",
    "jenis_kelamin": "L",
    "alamat_kabko": "BANGKA BARAT",
    "profile": {
      "id_calon_dpr": "fde4984b0e0b0b6e17130a71f2bd57cd514ea8611895b781714958e001de7d0d8424fe77735cb06e1eaf6f994a62e727c92aa1b0bb7e707a5475eea73bd57831un+V88NXG30kLuV7YlVVDeRgr0XJDzpW9+KXAucfgX8=",
      "logo_partai": "berkas-sipol/parpol/profil/gambar_parpol/1658983159_Logo%20Gelora%20Portrait.png",
      "status_publikasi": "Bersedia"
    },
    "id_partai": 77,
    "kode_dapil": "190504"
  },
  {
    "nomor_urut": 5,
    "foto": "https://infopemilu.kpu.go.id/dct/berkas-silon/calon/406086/pas_foto/1684155460_c03f8a94-f8bf-4a2d-9cf7-9ff12cab35a8.jpeg",
    "nama": "MARIA YUSTIANA SUTA",
    "jenis_kelamin": "P",
    "alamat_kabko": "BANGKA BARAT",
    "profile": {
      "id_calon_dpr": "97a6049daae04cb68ec5acdb75274b6f57543a7c39d7c1c78bf3db5244b6478e165b1367134cd75e7c71d4b5066dc1d4d344dd46415bb210a738932dad2cf212SKttlFypYs5nYujdNQk4sdP0sOBdBC5sgQxm7V17aDI=",
      "logo_partai": "berkas-sipol/parpol/profil/gambar_parpol/1658983159_Logo%20Gelora%20Portrait.png",
      "status_publikasi": "Bersedia"
    },
    "id_partai": 77,
    "kode_dapil": "190504"
  },
  {
    "nomor_urut": 6,
    "foto": "https://infopemilu.kpu.go.id/dct/berkas-silon/calon/406087/pas_foto/1684156114_fbf97037-1943-435c-99a0-e9bce63c7851.jpeg",
    "nama": "MUJIYEM",
    "jenis_kelamin": "P",
    "alamat_kabko": "BANGKA BARAT",
    "profile": {
      "id_calon_dpr": "cfc1c469f6850c8f825b784179dc0ccf904e9ca9296db5de73a7a08b67275cbdafd077d057373b92ded7a517b47d8e5401426ddb218df12004d9566c99e05b81r/wHtIXtoJbg7MRbIUipSeQehS1XRnR3ao2UgzlhUxQ=",
      "logo_partai": "berkas-sipol/parpol/profil/gambar_parpol/1658983159_Logo%20Gelora%20Portrait.png",
      "status_publikasi": "Bersedia"
    },
    "id_partai": 77,
    "kode_dapil": "190504"
  },
  {
    "nomor_urut": 1,
    "foto": "https://infopemilu.kpu.go.id/dct/berkas-silon/calon/135189/pas_foto/1683533843_d170cf39-3c5f-4462-8bcc-7ea596746d2a.jpeg",
    "nama": "SYAHBANDAR",
    "jenis_kelamin": "L",
    "alamat_kabko": "BANGKA BARAT",
    "profile": {
      "id_calon_dpr": "93e1de2e600a0aa9c1e07b34fd11629f398faeb4e60565b1bed617b44fa925804c2f3cc22b19b59ab891e6d58f4da3e71bd7fda210d827feeb3f8e7f1ecb3f5dVISv7v46HYW80zl4MpQuUCrUjjhUTZm1wwCy1H+PjxM=",
      "logo_partai": "berkas-sipol/parpol/profil/gambar_parpol/1656395115_lambang_pks.png",
      "status_publikasi": "Bersedia"
    },
    "id_partai": 6,
    "kode_dapil": "190504"
  },
  {
    "nomor_urut": 2,
    "foto": "https://infopemilu.kpu.go.id/dct/berkas-silon/calon/135924/pas_foto/1683473929_bc3e988d-8e07-46d5-9039-3a7dd4fbb181.jpeg",
    "nama": "ANDI",
    "jenis_kelamin": "L",
    "alamat_kabko": "BANGKA BARAT",
    "profile": {
      "id_calon_dpr": "08cec4cceebdc30235da9adeb4387cd793384223effea89fbb34a6e25b2d86e8762c1d2735f7d256562041a20eabda24ad4fb1cf455fa495bda51ff354d794e1ESvz28pj6NSmb5MEpki+sHEZ07JofoGtHEsN6baJq00=",
      "logo_partai": "berkas-sipol/parpol/profil/gambar_parpol/1656395115_lambang_pks.png",
      "status_publikasi": "Bersedia"
    },
    "id_partai": 6,
    "kode_dapil": "190504"
  },
  {
    "nomor_urut": 3,
    "foto": "https://infopemilu.kpu.go.id/dct/berkas-silon/calon/136175/pas_foto/1688630003_c2d9adc6-822d-4d34-ae61-5516d1c1b894.jpeg",
    "nama": "JUNURIAH",
    "jenis_kelamin": "P",
    "alamat_kabko": "BANGKA BARAT",
    "profile": {
      "id_calon_dpr": "dc72b5fa4cc0f0b01aaf31df90d94c8d6d14b978f7f1e6dfdb430501e62fe888c6e62a5c3055ce7cfa18f9934408f3d7ae59b25b88ee904a24f26bfe9c84e95cCa8X8NJg0kB24QpvX6ysmSNWq0zuzRZgiyhbL6tgi/g=",
      "logo_partai": "berkas-sipol/parpol/profil/gambar_parpol/1656395115_lambang_pks.png",
      "status_publikasi": "Bersedia"
    },
    "id_partai": 6,
    "kode_dapil": "190504"
  },
  {
    "nomor_urut": 4,
    "foto": "https://infopemilu.kpu.go.id/dct/berkas-silon/calon/136284/pas_foto/1683475133_c79bc8b4-b89d-4b50-b3c7-3649374bd6b8.jpeg",
    "nama": "KEMI",
    "jenis_kelamin": "L",
    "alamat_kabko": "BANGKA BARAT",
    "profile": {
      "id_calon_dpr": "289d823c6b2ef19bcbf6a10827e41e1a36d47de76992bc1dad55dae7a06598eff2da1d51b8a1577c22dd12871dc065b12fc18673afadd93af978be8c140e9fa62wpQBi6h/jAOw+wRFh0GP2VCFhRJrQL1qJOyX5oIIZw=",
      "logo_partai": "berkas-sipol/parpol/profil/gambar_parpol/1656395115_lambang_pks.png",
      "status_publikasi": "Bersedia"
    },
    "id_partai": 6,
    "kode_dapil": "190504"
  },
  {
    "nomor_urut": 5,
    "foto": "https://infopemilu.kpu.go.id/dct/berkas-silon/calon/136401/pas_foto/1683533236_923fb4f0-2f8e-4168-9c35-9f4bddebc93d.jpeg",
    "nama": "JOHANSYAH",
    "jenis_kelamin": "L",
    "alamat_kabko": "BANGKA BARAT",
    "profile": {
      "id_calon_dpr": "78ab225f6deb7961dda1cdbd0fbea0a7036ce01813a4704569163b1b4e1e450f15aacd50f89e6b6f80d237289fb5dfe3bc5f58a5c607bc9c679bc122b550bf2d0bIFTR1JWN7kk0MxFWfoTue6K5d7ADXaRvBbAOinEQ8=",
      "logo_partai": "berkas-sipol/parpol/profil/gambar_parpol/1656395115_lambang_pks.png",
      "status_publikasi": "Bersedia"
    },
    "id_partai": 6,
    "kode_dapil": "190504"
  },
  {
    "nomor_urut": 6,
    "foto": "https://infopemilu.kpu.go.id/dct/berkas-silon/calon/450300/pas_foto/1688785592_8c7519f5-7e0f-4267-823d-17fc81e2e6dc.jpeg",
    "nama": "SARTINI",
    "jenis_kelamin": "P",
    "alamat_kabko": "BANGKA BARAT",
    "profile": {
      "id_calon_dpr": "c6c00c4f6c326e120ca762510d52b3621b2fc1f472469897121a30b6119b2f8a34f15a175c7bb53717fbefe6f7ab81cc84ed35f43220f493298638cc8f666d65Vl3EH3aJYRQlQpLleviC6KZhBctclyRfswUdXT4UV9I=",
      "logo_partai": "berkas-sipol/parpol/profil/gambar_parpol/1656395115_lambang_pks.png",
      "status_publikasi": "Bersedia"
    },
    "id_partai": 6,
    "kode_dapil": "190504"
  },
  {
    "nomor_urut": 7,
    "foto": "https://infopemilu.kpu.go.id/dct/berkas-silon/calon/136528/pas_foto/1683529594_4ef3baa8-fde5-443a-a138-f67558e340f4.jpeg",
    "nama": "MUHAMMAD RIFKI NAUVALDI",
    "jenis_kelamin": "L",
    "alamat_kabko": "BANGKA BARAT",
    "profile": {
      "id_calon_dpr": "5c74387578ebdad8bd56e55e8544d054de549bbb82807bc0a87b8fcd2e1bc69b1e2fbad1b9b80355a77db42b7157582f594f24f08a0a6ad263f213ac2d1cae199bX/IrPOAqSlbziL7RcZID6rEb7qFXqBQ7E1tuV2Hdo=",
      "logo_partai": "berkas-sipol/parpol/profil/gambar_parpol/1656395115_lambang_pks.png",
      "status_publikasi": "Bersedia"
    },
    "id_partai": 6,
    "kode_dapil": "190504"
  },
  {
    "nomor_urut": 8,
    "foto": "https://infopemilu.kpu.go.id/dct/berkas-silon/calon/136134/pas_foto/1683530147_0dec9d27-fa70-41bc-a6ae-a72cc6c8651c.jpeg",
    "nama": "LUPITA SARI",
    "jenis_kelamin": "P",
    "alamat_kabko": "BANGKA BARAT",
    "profile": {
      "id_calon_dpr": "ba9d08db11a409787e461d820823a358b2683fe482d88db035d155f10deb013129319c6a7bbfd4603830346f47389db8bcf3673d1b5390115ef22fed82afe1d8sFDwJgHRidb9ecl2BOgDGBNNrcinI08bIHaNoKaRkHQ=",
      "logo_partai": "berkas-sipol/parpol/profil/gambar_parpol/1656395115_lambang_pks.png",
      "status_publikasi": "Bersedia"
    },
    "id_partai": 6,
    "kode_dapil": "190504"
  },
  {
    "nomor_urut": 9,
    "foto": "https://infopemilu.kpu.go.id/dct/berkas-silon/calon/469893/pas_foto/1691565121_50982c49-e458-4fb5-ae0a-a3d7c43be8a4.jpeg",
    "nama": "YAN JUANDA",
    "jenis_kelamin": "L",
    "alamat_kabko": "BANGKA BARAT",
    "profile": {
      "id_calon_dpr": "72ad6885dd3227a9a282c59fa94b334147a8620e803e32ed444aa596e77132cab4551b86b25890e0f83c8871bb47b86c053d3bb037a481bac5e64980d5c83535RxKYTuF75Eyf+9pYGEokjK6sneaa04mhSoOk6YuBjas=",
      "logo_partai": "berkas-sipol/parpol/profil/gambar_parpol/1656395115_lambang_pks.png",
      "status_publikasi": "Bersedia"
    },
    "id_partai": 6,
    "kode_dapil": "190504"
  },
  {
    "nomor_urut": 1,
    "foto": "https://infopemilu.kpu.go.id/dct/berkas-silon/calon/33429/pas_foto/1683104065_ab195524-a316-47f9-8595-214426823827.jpeg",
    "nama": "RIANDA PRATAMA",
    "jenis_kelamin": "L",
    "alamat_kabko": "BANGKA BARAT",
    "profile": {
      "id_calon_dpr": "39397d4f6ff332342a1170e7d4a075ebc10c600252f675a2a6f2e92dbae05df1088aaab539b392858105645503130aa72af67b301993af3e1f40b38019650eeb/VJr9GKPqAn3q1xVkXlV2vV6QfEMdOaRazu4v+FKpUk=",
      "logo_partai": "berkas-sipol/parpol/profil/gambar_parpol/1656155242_logo%20PKN-.png",
      "status_publikasi": "Bersedia"
    },
    "id_partai": 26,
    "kode_dapil": "190504"
  },
  {
    "nomor_urut": 2,
    "foto": "https://infopemilu.kpu.go.id/dct/berkas-silon/calon/31222/pas_foto/1688817585_80da494f-6ccd-4309-978e-388760264149.jpeg",
    "nama": "DESI INTAN PERMATA DURI, S.Kep",
    "jenis_kelamin": "P",
    "alamat_kabko": "BANGKA BARAT",
    "profile": {
      "id_calon_dpr": "b5c28332f4b9c6cb86c9d0a92ef6eca44ea83424e703ec64a69a4765a8f0b7f617a16623ad3a7db63010427f27df858bdaab0fd22f21d14f3696e28f9cb79723a/4w6sqqB+ufSQRSVI98moqwYBYQrmyFtZF7jVr0WC0=",
      "logo_partai": "berkas-sipol/parpol/profil/gambar_parpol/1656155242_logo%20PKN-.png",
      "status_publikasi": "Bersedia"
    },
    "id_partai": 26,
    "kode_dapil": "190504"
  },
  {
    "nomor_urut": 3,
    "foto": "https://infopemilu.kpu.go.id/dct/berkas-silon/calon/126841/pas_foto/1683457755_769b2d0c-d5d9-42f0-a11b-9d1d1db3a6f2.jpeg",
    "nama": "KAMARUDIN",
    "jenis_kelamin": "L",
    "alamat_kabko": "BANGKA BARAT",
    "profile": {
      "id_calon_dpr": "5e526f8e40f300d42b4d4f16dedcd5e12efe609a368d03036fb10d08bc7fdedbad8f487a439795f481262ae89a13dbc14411b742437989568353f458431f6a52mCvQH5i7Q6w8mKC2yXEaPiajaYikvUHdxJQtwOSCTIg=",
      "logo_partai": "berkas-sipol/parpol/profil/gambar_parpol/1656155242_logo%20PKN-.png",
      "status_publikasi": "Bersedia"
    },
    "id_partai": 26,
    "kode_dapil": "190504"
  },
  {
    "nomor_urut": 4,
    "foto": "https://infopemilu.kpu.go.id/dct/berkas-silon/calon/126339/pas_foto/1683521629_008603da-caf3-4033-b537-0954ed62d888.jpeg",
    "nama": "IKE REZIKA",
    "jenis_kelamin": "P",
    "alamat_kabko": "BANGKA BARAT",
    "profile": {
      "id_calon_dpr": "da051152fe74634ab8b29407aeb516b03e4c67e1d27987522d118c3611a6079f66c1b9dd372a39f99d420255a582df1fbde45a8427272046c9dc027b31d6482cQADIw9z03Ea+M4133VfdyjOIkAl05ioXAKZ+RwvSAK8=",
      "logo_partai": "berkas-sipol/parpol/profil/gambar_parpol/1656155242_logo%20PKN-.png",
      "status_publikasi": "Bersedia"
    },
    "id_partai": 26,
    "kode_dapil": "190504"
  },
  {
    "nomor_urut": 1,
    "foto": "https://infopemilu.kpu.go.id/dct/berkas-silon/calon/35136/pas_foto/1683103291_e5d30a93-84e8-4505-87ee-752667de8a44.jpeg",
    "nama": "EKO FENDIKA PUTRA, S.T.",
    "jenis_kelamin": "L",
    "alamat_kabko": "BANGKA BARAT",
    "profile": {
      "id_calon_dpr": "663fb6e48c1379d83eda36650aec4148afabc2c229bc3b7aadb91d1d082972bd4235fcb824497e8f43d939663e363ff638e667647f0828dcc140bafc2a080f65ajx2SD2xt2r6dgrEPLeuqAoKS6Bt4LKM/o05fXKqlNA=",
      "logo_partai": "berkas-sipol/parpol/profil/gambar_parpol/1659263373_hanura_10x10.png",
      "status_publikasi": "Bersedia"
    },
    "id_partai": 5,
    "kode_dapil": "190504"
  },
  {
    "nomor_urut": 2,
    "foto": "https://infopemilu.kpu.go.id/dct/berkas-silon/calon/35407/pas_foto/1683104164_18008b26-4d13-44ab-a4b8-7e6fe731a193.jpeg",
    "nama": "MASRAN, S.Pd.Mat",
    "jenis_kelamin": "L",
    "alamat_kabko": "BANGKA BARAT",
    "profile": {
      "id_calon_dpr": "f78b8832b6161e2d8a066554d560fa2291de5d51458e91946ec6d59edffc6b22189bd2cb9fd6dfa62755fdf92a97325f5985bc5367d990cfdf374116e30d46f2XyXjcPsFFsmEdDJNA/fyZVfG7KyRVrtv2Ebf/0eviQk=",
      "logo_partai": "berkas-sipol/parpol/profil/gambar_parpol/1659263373_hanura_10x10.png",
      "status_publikasi": "Bersedia"
    },
    "id_partai": 5,
    "kode_dapil": "190504"
  },
  {
    "nomor_urut": 3,
    "foto": "https://infopemilu.kpu.go.id/dct/berkas-silon/calon/320982/pas_foto/1683882643_6e7f601b-6266-4682-a723-9c7f07f98856.jpeg",
    "nama": "RESTI LESMAYDA",
    "jenis_kelamin": "P",
    "alamat_kabko": "BANGKA BARAT",
    "profile": {
      "id_calon_dpr": "b515c0fd565fd0b759c09b4bf57b6155cfdbb24331ab4576c2107950f096c5ecd2411d3f87c7acf3d9ce21e3f528429c7a689601d306c6174b6975a5a87028591/1Q2n8SMy/clerWeNi5pTolV5qSRDWJtT+iXdCI100=",
      "logo_partai": "berkas-sipol/parpol/profil/gambar_parpol/1659263373_hanura_10x10.png",
      "status_publikasi": "Bersedia"
    },
    "id_partai": 5,
    "kode_dapil": "190504"
  },
  {
    "nomor_urut": 4,
    "foto": "https://infopemilu.kpu.go.id/dct/berkas-silon/calon/84761/pas_foto/1683358469_d8ceb405-36aa-424c-9921-ea9bbb4ec4a3.jpeg",
    "nama": "NADIANTO",
    "jenis_kelamin": "L",
    "alamat_kabko": "BANGKA BARAT",
    "profile": {
      "id_calon_dpr": "8bed7a447d04db7276e5fafccbd48554f5dc2fce8dd5805a3fbc82d4cced22f7408533ce0ff1663bc47f440830828aa03b20f874122ad5fc51c297226e530e031ql3beFBnz7jyrWdC8s8n2n20cYW0sqSdulk+SXZuIE=",
      "logo_partai": "berkas-sipol/parpol/profil/gambar_parpol/1659263373_hanura_10x10.png",
      "status_publikasi": "Bersedia"
    },
    "id_partai": 5,
    "kode_dapil": "190504"
  },
  {
    "nomor_urut": 5,
    "foto": "https://infopemilu.kpu.go.id/dct/berkas-silon/calon/35319/pas_foto/1683103936_18be5a92-6724-4ada-b0b5-963b9ea989b0.jpeg",
    "nama": "APENDI",
    "jenis_kelamin": "L",
    "alamat_kabko": "BANGKA BARAT",
    "profile": {
      "id_calon_dpr": "c099bf5f7bb993b08bb8f45fecd79d0a3b7a7a6ced6e8525e81ae4ab2ff5b6c73f524a30c52d24c04380530bcc256208eace9e6b50b1011d76681f7fe199d7ebTXWoYZNU29K72fRJHPAsgTgQXpTDGyBjEuTIdRaU0vc=",
      "logo_partai": "berkas-sipol/parpol/profil/gambar_parpol/1659263373_hanura_10x10.png",
      "status_publikasi": "Bersedia"
    },
    "id_partai": 5,
    "kode_dapil": "190504"
  },
  {
    "nomor_urut": 6,
    "foto": "https://infopemilu.kpu.go.id/dct/berkas-silon/calon/150354/pas_foto/1683532015_1f48cfcb-2b7d-4c3f-82d8-4b0f5d165707.jpeg",
    "nama": "TRIA MONIKA",
    "jenis_kelamin": "P",
    "alamat_kabko": "BANGKA BARAT",
    "profile": {
      "id_calon_dpr": "ef1cc3eff3182e6103aa62c4b69d334a77d43af239a8cc90f83b145f3a32bab9f2cd98180281e71ac697d8873507279058df0e366a9c86919e06f5e9fad229261AJTM1gtnYbyGHbxKESAcFfaLzaG/px2g/biTf3iTpw=",
      "logo_partai": "berkas-sipol/parpol/profil/gambar_parpol/1659263373_hanura_10x10.png",
      "status_publikasi": "Bersedia"
    },
    "id_partai": 5,
    "kode_dapil": "190504"
  },
  {
    "nomor_urut": 7,
    "foto": "https://infopemilu.kpu.go.id/dct/berkas-silon/calon/80010/pas_foto/1683350827_23c03878-dbda-46b9-b868-68040608e711.jpeg",
    "nama": "BENI",
    "jenis_kelamin": "L",
    "alamat_kabko": "BANGKA BARAT",
    "profile": {
      "id_calon_dpr": "52f6b17c16fe99e0c3216bab31ea417fc53fa53559e06840027478bbf12e96f1be7846605b752419fd4d798499d8b04e1c70d82eb63a941ef4579dc36c7d40476IeotyEoK96O+P9nKh8RXK7iXYPKAlCXjdifBxD1nkQ=",
      "logo_partai": "berkas-sipol/parpol/profil/gambar_parpol/1659263373_hanura_10x10.png",
      "status_publikasi": "Bersedia"
    },
    "id_partai": 5,
    "kode_dapil": "190504"
  },
  {
    "nomor_urut": 8,
    "foto": "https://infopemilu.kpu.go.id/dct/berkas-silon/calon/35275/pas_foto/1683103785_16a42aae-dd1f-4b92-b85d-ac0aad4591e9.jpeg",
    "nama": "SINDI SANORA",
    "jenis_kelamin": "P",
    "alamat_kabko": "BANGKA BARAT",
    "profile": {
      "id_calon_dpr": "aaf23570f48fb5532e71da5a3092709882e57f25986073c2fa8fb2bc11562f2d35aba4677d64eb66af9e91da719731556abc836f8ed269ef9f8d33c8234cc35cCv5hbC6x/fo2cxJ1HymrfMMYDHVODxJdx1ELN/dU6ew=",
      "logo_partai": "berkas-sipol/parpol/profil/gambar_parpol/1659263373_hanura_10x10.png",
      "status_publikasi": "Bersedia"
    },
    "id_partai": 5,
    "kode_dapil": "190504"
  },
  {
    "nomor_urut": 9,
    "foto": "https://infopemilu.kpu.go.id/dct/berkas-silon/calon/35226/pas_foto/1683103584_654132f0-80da-45e5-a356-8c0c7d80a067.jpeg",
    "nama": "ZARMINDI",
    "jenis_kelamin": "L",
    "alamat_kabko": "BANGKA BARAT",
    "profile": {
      "id_calon_dpr": "6e61b7f6edef776396922cbe98dfe71fca680bb004e26ef986574d098bb4f8a20d9aac73ad50bb1a330fdccade4371e7d4d47ce61e559125eda1d46999440839MBoG2Po8kVbIpgFJ1UltrqZFDZ6XBNCBx4oemmzHL4M=",
      "logo_partai": "berkas-sipol/parpol/profil/gambar_parpol/1659263373_hanura_10x10.png",
      "status_publikasi": "Bersedia"
    },
    "id_partai": 5,
    "kode_dapil": "190504"
  },
  {
    "nomor_urut": 1,
    "foto": "https://infopemilu.kpu.go.id/dct/berkas-silon/calon/119593/pas_foto/1688789906_093d62e2-e788-40c9-b8c2-0f8dc1acc81a.jpeg",
    "nama": "DAFITRI, S.Sos",
    "jenis_kelamin": "L",
    "alamat_kabko": "BANGKA BARAT",
    "profile": {
      "id_calon_dpr": "21e34687d5e89fd20c23146a4780e8b36d1019c933da27f87c4935b0be3cc29deebf67a381b97360d919d7e03981b1017461d661341fbe7810babae33e628450KZd29Gkb5FOxMn0SvaPneCEF7uAsc7w7THqtThx0pa0=",
      "logo_partai": "berkas-sipol/parpol/profil/gambar_parpol/1656404797_LOGO%20PAN.png",
      "status_publikasi": "Bersedia"
    },
    "id_partai": 7,
    "kode_dapil": "190504"
  },
  {
    "nomor_urut": 2,
    "foto": "https://infopemilu.kpu.go.id/dct/berkas-silon/calon/102029/pas_foto/1688790125_79635c9a-2109-4425-9b1f-5b7c1e4915ef.jpeg",
    "nama": "HIJRAT MALJAM",
    "jenis_kelamin": "L",
    "alamat_kabko": "BANGKA BARAT",
    "profile": {
      "id_calon_dpr": "4951d36c5834ffc333341d1ffc5313b689a76e16448dc0c6e20910eb0f679ca25e13cb98f2c1c5bbd68e14c595d9c58da911c3c28efd3ab22ebfcc1cd0209fd5l7j8S/B1OKwWfG3OOeQNkqrpmXvIF5urjvZmsZfqVTk=",
      "logo_partai": "berkas-sipol/parpol/profil/gambar_parpol/1656404797_LOGO%20PAN.png",
      "status_publikasi": "Bersedia"
    },
    "id_partai": 7,
    "kode_dapil": "190504"
  },
  {
    "nomor_urut": 3,
    "foto": "https://infopemilu.kpu.go.id/dct/berkas-silon/calon/97646/pas_foto/1683446895_83d6b154-9453-4f5c-86ff-9cd2bed49e50.jpeg",
    "nama": "MANISA",
    "jenis_kelamin": "P",
    "alamat_kabko": "BANGKA BARAT",
    "profile": {
      "id_calon_dpr": "16b1546bd5b5db8175e611af6413c72e44f279ff9b3c333e273ca26b3c5f17f1bb3416f78175d9138e8a82fb1ef95a5561d970721fa05cc619f8c09531be7abeaR0uBDeeVU16430QwvyvGNlGe4+0Cl3uLNMbjkoVJB8=",
      "logo_partai": "berkas-sipol/parpol/profil/gambar_parpol/1656404797_LOGO%20PAN.png",
      "status_publikasi": "Bersedia"
    },
    "id_partai": 7,
    "kode_dapil": "190504"
  },
  {
    "nomor_urut": 4,
    "foto": "https://infopemilu.kpu.go.id/dct/berkas-silon/calon/98344/pas_foto/1683766439_2a9fd600-14c7-4a81-bf4d-0af7e98eb15a.jpeg",
    "nama": "SUMANTRI",
    "jenis_kelamin": "L",
    "alamat_kabko": "BANGKA BARAT",
    "profile": {
      "id_calon_dpr": "6841806cba74fd36d8fd9a6094a884e6d9e77532f5bd1ef3e38e0a1aea37650c4ea84f657d1d57aaedac790f70376298788a6d7f5b4a06ab6943a109c3b4437dRPPXlbEyiZbSmeU06j3fHmgbkLXVgBXr27TDahGjhAE=",
      "logo_partai": "berkas-sipol/parpol/profil/gambar_parpol/1656404797_LOGO%20PAN.png",
      "status_publikasi": "Bersedia"
    },
    "id_partai": 7,
    "kode_dapil": "190504"
  },
  {
    "nomor_urut": 5,
    "foto": "https://infopemilu.kpu.go.id/dct/berkas-silon/calon/119451/pas_foto/1683446632_7fc0dddb-a8f1-42e8-81a9-10274c0c4077.jpeg",
    "nama": "AMRI",
    "jenis_kelamin": "L",
    "alamat_kabko": "BANGKA BARAT",
    "profile": {
      "id_calon_dpr": "cf8c4e59fab294ce3b4ae738306dc163eae2a1db7be146ca24adea8e5eefcc75bf506024db89c9320a61bc24be74ae9a1d403311e909bc7db0ac7e30f0f8ff10ihHXsCqAjyGWqhli8GkJC/HOPC26BzwH7mY2/TD0ZJ8=",
      "logo_partai": "berkas-sipol/parpol/profil/gambar_parpol/1656404797_LOGO%20PAN.png",
      "status_publikasi": "Bersedia"
    },
    "id_partai": 7,
    "kode_dapil": "190504"
  },
  {
    "nomor_urut": 6,
    "foto": "https://infopemilu.kpu.go.id/dct/berkas-silon/calon/182996/pas_foto/1683745322_018e5e8b-632f-4eda-adc9-e93f4fbe7507.jpeg",
    "nama": "PISMA ROKIYAH",
    "jenis_kelamin": "P",
    "alamat_kabko": "BANGKA BARAT",
    "profile": {
      "id_calon_dpr": "31c7a44ea4c97fe612adddbf8d53c5fe1bf72a6f438ef37135482525fcaea730ead108b0152189a5eafb7e0f4338faca74b27c06870ce67dab2f305aaaa2c007LsGjN/OCh0oCXnyAPJFkBkzEqQFb9CsSArPoUnBW0Eo=",
      "logo_partai": "berkas-sipol/parpol/profil/gambar_parpol/1656404797_LOGO%20PAN.png",
      "status_publikasi": "Bersedia"
    },
    "id_partai": 7,
    "kode_dapil": "190504"
  },
  {
    "nomor_urut": 7,
    "foto": "https://infopemilu.kpu.go.id/dct/berkas-silon/calon/183062/pas_foto/1688788280_e8ecddf6-a04d-439a-a89e-d3fdfebae261.jpeg",
    "nama": "ABDURACHMAN SHIHAB",
    "jenis_kelamin": "L",
    "alamat_kabko": "BANGKA BARAT",
    "profile": {
      "id_calon_dpr": "73eb39494fd71b0714a1a333a215746a66fa69e9612dd25ebc3fb504022dc0168e68fa42162027f5c899faec1726151a21b99ae3def80612c0b82a1677369b15YAw2Ehv+jkqarou1E9EehdyOs1nvA4rgfi7eFAQJbqM=",
      "logo_partai": "berkas-sipol/parpol/profil/gambar_parpol/1656404797_LOGO%20PAN.png",
      "status_publikasi": "Bersedia"
    },
    "id_partai": 7,
    "kode_dapil": "190504"
  },
  {
    "nomor_urut": 8,
    "foto": "https://infopemilu.kpu.go.id/dct/berkas-silon/calon/102013/pas_foto/1683446978_f22dc8fe-5782-4fe2-9f49-f337ac114c74.jpeg",
    "nama": "KENAN",
    "jenis_kelamin": "L",
    "alamat_kabko": "BANGKA BARAT",
    "profile": {
      "id_calon_dpr": "c33aff1b25eff790821d34b693c7ecf364f502d547ac5c0d8ca4c8a04342d686724a8b1fbb3d6a164af74023b108964f5636a8be3ff32d88c2a4d8ada4e31133TefVfIvcFS4ypygbDy7Ds2WqjnEpxBPa23RCF77au6g=",
      "logo_partai": "berkas-sipol/parpol/profil/gambar_parpol/1656404797_LOGO%20PAN.png",
      "status_publikasi": "Bersedia"
    },
    "id_partai": 7,
    "kode_dapil": "190504"
  },
  {
    "nomor_urut": 9,
    "foto": "https://infopemilu.kpu.go.id/dct/berkas-silon/calon/183100/pas_foto/1688793251_9e8e9102-0165-4aa9-98a6-95a38f4bce01.jpeg",
    "nama": "RESTU DAMAYANTI, S.E.",
    "jenis_kelamin": "P",
    "alamat_kabko": "BANGKA BARAT",
    "profile": {
      "id_calon_dpr": "10a84c1c44d82ace664a9a3ff155499b74bb7b53027839dda81f26e47b5ee32c379254af12742beb804cff14d545667eda0ecaa294df6d7946d8e96e8aaa68b6M/+cRMBrpXVLq1RJb4m9ZbI5wakNG8rPQBX2R2UXKas=",
      "logo_partai": "berkas-sipol/parpol/profil/gambar_parpol/1656404797_LOGO%20PAN.png",
      "status_publikasi": "Bersedia"
    },
    "id_partai": 7,
    "kode_dapil": "190504"
  },
  {
    "nomor_urut": 1,
    "foto": "https://infopemilu.kpu.go.id/dct/berkas-silon/calon_unggah/42440/pas_foto/1905043008970001.jpg",
    "nama": "DEDI EGIPTY, S.H.",
    "jenis_kelamin": "L",
    "alamat_kabko": "BANGKA BARAT",
    "profile": {},
    "id_partai": 74,
    "kode_dapil": "190504"
  },
  {
    "nomor_urut": 2,
    "foto": "https://infopemilu.kpu.go.id/dct/berkas-silon/calon/265890/pas_foto/1688797476_548bce82-8ecc-4d22-920a-53ee10798cb1.jpeg",
    "nama": "SUHENTI PUTRI NINGSIH",
    "jenis_kelamin": "P",
    "alamat_kabko": "BANGKA BARAT",
    "profile": {},
    "id_partai": 74,
    "kode_dapil": "190504"
  },
  {
    "nomor_urut": 3,
    "foto": "https://infopemilu.kpu.go.id/dct/berkas-silon/calon_unggah/42440/pas_foto/1905041401800001.jpg",
    "nama": "TARMIZI, S.E",
    "jenis_kelamin": "L",
    "alamat_kabko": "BANGKA BARAT",
    "profile": {},
    "id_partai": 74,
    "kode_dapil": "190504"
  },
  {
    "nomor_urut": 4,
    "foto": "https://infopemilu.kpu.go.id/dct/berkas-silon/calon/265892/pas_foto/1688804213_f7b98851-3d33-4fa0-b92e-c68f4e1ea50f.jpeg",
    "nama": "REMOBON",
    "jenis_kelamin": "L",
    "alamat_kabko": "BANGKA BARAT",
    "profile": {},
    "id_partai": 74,
    "kode_dapil": "190504"
  },
  {
    "nomor_urut": 5,
    "foto": "https://infopemilu.kpu.go.id/dct/berkas-silon/calon_unggah/42440/pas_foto/1905041809730002.jpg",
    "nama": "KASIRUN",
    "jenis_kelamin": "L",
    "alamat_kabko": "BANGKA BARAT",
    "profile": {},
    "id_partai": 74,
    "kode_dapil": "190504"
  },
  {
    "nomor_urut": 6,
    "foto": "https://infopemilu.kpu.go.id/dct/berkas-silon/calon/265894/pas_foto/1688801160_a6de8e03-10a1-4ec3-92cd-6e8ce8615e6b.jpeg",
    "nama": "RUSMANA",
    "jenis_kelamin": "P",
    "alamat_kabko": "BANGKA BARAT",
    "profile": {},
    "id_partai": 74,
    "kode_dapil": "190504"
  },
  {
    "nomor_urut": 7,
    "foto": "https://infopemilu.kpu.go.id/dct/berkas-silon/calon/265895/pas_foto/1688804260_7b6cce4a-b236-4732-83e5-31506a9d91be.jpeg",
    "nama": "SANDI MARIO, S.Kom",
    "jenis_kelamin": "L",
    "alamat_kabko": "BANGKA BARAT",
    "profile": {},
    "id_partai": 74,
    "kode_dapil": "190504"
  },
  {
    "nomor_urut": 8,
    "foto": "https://infopemilu.kpu.go.id/dct/berkas-silon/calon/453251/pas_foto/1688804994_6e86d292-d821-474e-bd03-1ef9e0a2177d.jpeg",
    "nama": "RENSI LESTARI",
    "jenis_kelamin": "P",
    "alamat_kabko": "BANGKA BARAT",
    "profile": {},
    "id_partai": 74,
    "kode_dapil": "190504"
  },
  {
    "nomor_urut": 9,
    "foto": "https://infopemilu.kpu.go.id/dct/berkas-silon/calon/265897/pas_foto/1688804163_8f954586-04b0-4c8d-af4d-edbdb227bcae.jpeg",
    "nama": "SYAMSUL",
    "jenis_kelamin": "L",
    "alamat_kabko": "BANGKA BARAT",
    "profile": {},
    "id_partai": 74,
    "kode_dapil": "190504"
  },
  {
    "nomor_urut": 1,
    "foto": "https://infopemilu.kpu.go.id/dct/berkas-silon/calon_unggah/100756/pas_foto/1905040506770001.jpg",
    "nama": "IZKAR",
    "jenis_kelamin": "L",
    "alamat_kabko": "BANGKA BARAT",
    "profile": {
      "id_calon_dpr": "951dfee21efe5cd599712e78d79e17af6cf39cba5a5976331bd0010bccca7c31ac376b291559c4a59011141606aa356e4af03c0d222101d4309938d02c88c51aS6dgvjM2aXL5X1v6XnqOSbzSshASOmGpfC+iX8nulxU=",
      "logo_partai": "berkas-sipol/parpol/profil/gambar_parpol/1656229496_WhatsApp%20Image%202022-06-26%20at%201.53.14%20PM.png",
      "status_publikasi": "Bersedia"
    },
    "id_partai": 13,
    "kode_dapil": "190504"
  },
  {
    "nomor_urut": 2,
    "foto": "https://infopemilu.kpu.go.id/dct/berkas-silon/calon_unggah/100756/pas_foto/1905040211890002.jpg",
    "nama": "ACHKIKY, S.Kep",
    "jenis_kelamin": "L",
    "alamat_kabko": "BANGKA BARAT",
    "profile": {
      "id_calon_dpr": "783ff03108d2c819e8cb63d4c99571dc2cc65c1a545fed5b1761bbc0fbbe99fa0114159c587ea31bb2716b512baabd809871346840f522f19351b5021f244fb4BIJzZoyHb1QqjN/y4pXOkgLDL3lgrJ7xM3F3UKSSO8w=",
      "logo_partai": "berkas-sipol/parpol/profil/gambar_parpol/1656229496_WhatsApp%20Image%202022-06-26%20at%201.53.14%20PM.png",
      "status_publikasi": "Bersedia"
    },
    "id_partai": 13,
    "kode_dapil": "190504"
  },
  {
    "nomor_urut": 3,
    "foto": "https://infopemilu.kpu.go.id/dct/berkas-silon/calon/68655/pas_foto/1691646752_7c72a404-32dc-40bf-ad63-bb676a11f73b.jpeg",
    "nama": "DWI MERDA RIANGGANI, S.A.P.",
    "jenis_kelamin": "P",
    "alamat_kabko": "BANGKA BARAT",
    "profile": {
      "id_calon_dpr": "77cce9465f8d56e90c4cbce3c2c8532bf5cd5e78bf82b177de49fd0edbdb216a6f4263d91b65ded2b309ab2a7aa0949d52b5970e99c212d483fdeb8c6bad24d7Zm0OsmbRUpPS+/amtNWLYIZHCrC+zSBNV4mWLQ9tScY=",
      "logo_partai": "berkas-sipol/parpol/profil/gambar_parpol/1656229496_WhatsApp%20Image%202022-06-26%20at%201.53.14%20PM.png",
      "status_publikasi": "Bersedia"
    },
    "id_partai": 13,
    "kode_dapil": "190504"
  },
  {
    "nomor_urut": 4,
    "foto": "https://infopemilu.kpu.go.id/dct/berkas-silon/calon_unggah/100756/pas_foto/1905041608570001.jpg",
    "nama": "SAYUTI",
    "jenis_kelamin": "L",
    "alamat_kabko": "BANGKA BARAT",
    "profile": {
      "id_calon_dpr": "3df30da490a2db2658ce0e70bc655dde493df587473f9ec31b7334db234ce8e9bd881fff6b960a9d76f28173f460d12492a49d277cb0b3ed49653439fa1faabcX7enDaesR7MLKUazysmhI2FHvJoG1KSx60GwXTHoOQk=",
      "logo_partai": "berkas-sipol/parpol/profil/gambar_parpol/1656229496_WhatsApp%20Image%202022-06-26%20at%201.53.14%20PM.png",
      "status_publikasi": "Bersedia"
    },
    "id_partai": 13,
    "kode_dapil": "190504"
  },
  {
    "nomor_urut": 5,
    "foto": "https://infopemilu.kpu.go.id/dct/berkas-silon/calon/449711/pas_foto/1691647330_f27a9aef-cf03-4420-ba9a-9f5066dac6a3.jpeg",
    "nama": "SANDALI, S.P.",
    "jenis_kelamin": "L",
    "alamat_kabko": "BANGKA BARAT",
    "profile": {
      "id_calon_dpr": "0410e2f641113c4368229f78864795130208688ca7a4f750982b26eb02c3f5dd99a32395f04b59ff024279089acb9ae1d3b1da2a8bad75af9317b347186e14b6quW+gPgXZQ4x+QDU36BvjWHdnkgo70UIRMVq/B8uDDg=",
      "logo_partai": "berkas-sipol/parpol/profil/gambar_parpol/1656229496_WhatsApp%20Image%202022-06-26%20at%201.53.14%20PM.png",
      "status_publikasi": "Bersedia"
    },
    "id_partai": 13,
    "kode_dapil": "190504"
  },
  {
    "nomor_urut": 6,
    "foto": "https://infopemilu.kpu.go.id/dct/berkas-silon/calon_unggah/100756/pas_foto/1905046510990001.jpg",
    "nama": "WULAN SARI",
    "jenis_kelamin": "P",
    "alamat_kabko": "BANGKA BARAT",
    "profile": {
      "id_calon_dpr": "2aa5473253613c315b5fab2d29943f2b8ed1eb60d5ee2cba5b329c160d7a6e46e644e87b0f4d5f2dc4f08db5324322f5082d4c8a24d11c86e1b2b5d0315dfadcFIE4rshePoxxKf0k4hWr+4VSuNlGAY/fY7abEK5M/sA=",
      "logo_partai": "berkas-sipol/parpol/profil/gambar_parpol/1656229496_WhatsApp%20Image%202022-06-26%20at%201.53.14%20PM.png",
      "status_publikasi": "Bersedia"
    },
    "id_partai": 13,
    "kode_dapil": "190504"
  },
  {
    "nomor_urut": 7,
    "foto": "https://infopemilu.kpu.go.id/dct/berkas-silon/calon_unggah/100756/pas_foto/1905052912800001.jpg",
    "nama": "WASKITO",
    "jenis_kelamin": "L",
    "alamat_kabko": "BANGKA BARAT",
    "profile": {
      "id_calon_dpr": "abe935cfbab1908a43492fa28580bfb19524b9853b91df294f84a610901f6499cfae6a9ef2a809131f5a4ea63325478343e7675276bdeb44eb1bdde95eb3a83edaHjVfgZg/dOrD+O0QRo7Gv5eAaBPP+9br1P92IakgI=",
      "logo_partai": "berkas-sipol/parpol/profil/gambar_parpol/1656229496_WhatsApp%20Image%202022-06-26%20at%201.53.14%20PM.png",
      "status_publikasi": "Bersedia"
    },
    "id_partai": 13,
    "kode_dapil": "190504"
  },
  {
    "nomor_urut": 8,
    "foto": "https://infopemilu.kpu.go.id/dct/berkas-silon/calon_unggah/100756/pas_foto/1905034311860003.jpg",
    "nama": "MARYANI",
    "jenis_kelamin": "P",
    "alamat_kabko": "BANGKA BARAT",
    "profile": {
      "id_calon_dpr": "95c67f47839df450b214a188a134f85c83524d85467a59a685d826a412c23ab5209fa37f46e39250b083fced6138208a60c80cb74bf8d19f26416fac4ea1745aOYo9U+FUO3Vsbwt89q1M/gF72f9FMwwVhwVhesH0LeY=",
      "logo_partai": "berkas-sipol/parpol/profil/gambar_parpol/1656229496_WhatsApp%20Image%202022-06-26%20at%201.53.14%20PM.png",
      "status_publikasi": "Bersedia"
    },
    "id_partai": 13,
    "kode_dapil": "190504"
  },
  {
    "nomor_urut": 9,
    "foto": "https://infopemilu.kpu.go.id/dct/berkas-silon/calon_unggah/100756/pas_foto/1905041310920003.jpg",
    "nama": "GATOT WALOYO",
    "jenis_kelamin": "L",
    "alamat_kabko": "BANGKA BARAT",
    "profile": {
      "id_calon_dpr": "4f6a67469ac949d6a9dc8f7c089d17efe0537f3bd9c6f5c0e5851f0290b1ef96ec61ca18b16b679eddf63c614273ec3301f5723eb0a946a1c1074f4b785b085a9z4aVWEkk805uWjxwuaFHGMAGrPNLt7Pco5SWCdxi5Q=",
      "logo_partai": "berkas-sipol/parpol/profil/gambar_parpol/1656229496_WhatsApp%20Image%202022-06-26%20at%201.53.14%20PM.png",
      "status_publikasi": "Bersedia"
    },
    "id_partai": 13,
    "kode_dapil": "190504"
  },
  {
    "nomor_urut": 1,
    "foto": "https://infopemilu.kpu.go.id/dct/berkas-silon/calon/452306/pas_foto/1688799042_84783b06-21a6-412f-8e4c-0bbf55d42577.jpeg",
    "nama": "TERI ERLINA",
    "jenis_kelamin": "P",
    "alamat_kabko": "KOTA PANGKAL PINANG",
    "profile": {},
    "id_partai": 76,
    "kode_dapil": "190504"
  },
  {
    "nomor_urut": 1,
    "foto": "https://infopemilu.kpu.go.id/dct/berkas-silon/calon/39599/pas_foto/1691420784_cf384840-fa44-4193-8790-ee6758f3a07b.jpeg",
    "nama": "SITA ROSITA",
    "jenis_kelamin": "P",
    "alamat_kabko": "BANGKA BARAT",
    "profile": {
      "id_calon_dpr": "b99581682dca67d064d3eeb60b3fcc56dbfc3337213acca53af5b6820fb312ba6a9f0d1953078f5ba32a2e66db72170f2959b5f89faab1b6439f3ca9e4840303iQnYiIAxTAGItLOureOoZJhfeNO/1FaaRxyAhz5B9sA=",
      "logo_partai": "berkas-sipol/parpol/profil/gambar_parpol/1656144884_LOGO%20PARTAI%20PERINDO%2010x10%20cm%20(RGB).png",
      "status_publikasi": "Bersedia"
    },
    "id_partai": 18,
    "kode_dapil": "190504"
  },
  {
    "nomor_urut": 2,
    "foto": "https://infopemilu.kpu.go.id/dct/berkas-silon/calon/84890/pas_foto/1691420916_eac715f4-17a3-4e76-a2e0-dd03e9eace67.jpeg",
    "nama": "SUTARIYONO",
    "jenis_kelamin": "L",
    "alamat_kabko": "BANGKA BARAT",
    "profile": {
      "id_calon_dpr": "b5f84f144751aae68d1782876ae95242ff334f5e424cd03d50f6140b71a051f47bf4a0260c7369d01922d0c0a2536a2936814d52b6150424eae9cbc36545a5fa26DOpdf8Rm87tRYnv+kNbVXQMnwxKFfJtE5F+5pt05s=",
      "logo_partai": "berkas-sipol/parpol/profil/gambar_parpol/1656144884_LOGO%20PARTAI%20PERINDO%2010x10%20cm%20(RGB).png",
      "status_publikasi": "Bersedia"
    },
    "id_partai": 18,
    "kode_dapil": "190504"
  },
  {
    "nomor_urut": 3,
    "foto": "https://infopemilu.kpu.go.id/dct/berkas-silon/calon/56344/pas_foto/1688833961_e4431e64-860e-4422-b6ed-298b639e15c6.jpeg",
    "nama": "HERI EKO INDRIANTO, S.H",
    "jenis_kelamin": "L",
    "alamat_kabko": "KOTA PANGKAL PINANG",
    "profile": {
      "id_calon_dpr": "1f90967aff5f45da20b8a576d4561f60d3772179c5d959fef319f75dcc722af5000b97fe4514028ea32cc73ed1371477db464d0121900d43577533be2d89f1f4Rv66CwSiYsOyj1IsSEiX2Z5wQAr5QA3oHPBoZ5f46uY=",
      "logo_partai": "berkas-sipol/parpol/profil/gambar_parpol/1656144884_LOGO%20PARTAI%20PERINDO%2010x10%20cm%20(RGB).png",
      "status_publikasi": "Bersedia"
    },
    "id_partai": 18,
    "kode_dapil": "190504"
  },
  {
    "nomor_urut": 4,
    "foto": "https://infopemilu.kpu.go.id/dct/berkas-silon/calon/56826/pas_foto/1691421084_620ccaa8-3326-4de4-93df-b0ca1825203c.jpeg",
    "nama": "LIZAN",
    "jenis_kelamin": "L",
    "alamat_kabko": "BANGKA BARAT",
    "profile": {
      "id_calon_dpr": "c962f5b5ec0a3387461ba3209bacce7aadd33964fc8930bb1097c1f67f68f35e73a59792e86a428c0fdc0dc9169dd2c84d1868b7f466aeb3b12a90fe48874fcfzu/7HEPc8ASNVYBCL/fIDNvYHEzy736Cb0IacsK0FQc=",
      "logo_partai": "berkas-sipol/parpol/profil/gambar_parpol/1656144884_LOGO%20PARTAI%20PERINDO%2010x10%20cm%20(RGB).png",
      "status_publikasi": "Bersedia"
    },
    "id_partai": 18,
    "kode_dapil": "190504"
  },
  {
    "nomor_urut": 5,
    "foto": "https://infopemilu.kpu.go.id/dct/berkas-silon/calon/41153/pas_foto/1683211171_4c8e963d-f934-4906-9e4a-c95fe235f1f1.jpeg",
    "nama": "ANDI",
    "jenis_kelamin": "L",
    "alamat_kabko": "BANGKA BARAT",
    "profile": {
      "id_calon_dpr": "492ed132a689057378a83a0be9830ea462d5eb274a152812844a2dd37dd3f67de5de1376e5c5defe9545766b9786518aae20b7edc0a846bc9a8380aa8aadee59fKLZfrojglWAgCdgNzM3nEevUGrAqG+1UnQCdDrpXGM=",
      "logo_partai": "berkas-sipol/parpol/profil/gambar_parpol/1656144884_LOGO%20PARTAI%20PERINDO%2010x10%20cm%20(RGB).png",
      "status_publikasi": "Bersedia"
    },
    "id_partai": 18,
    "kode_dapil": "190504"
  },
  {
    "nomor_urut": 6,
    "foto": "https://infopemilu.kpu.go.id/dct/berkas-silon/calon/431193/pas_foto/1691389666_5441b58b-4920-4a5c-969e-3acc8f91e10d.jpeg",
    "nama": "LINDA",
    "jenis_kelamin": "P",
    "alamat_kabko": "BANGKA BARAT",
    "profile": {
      "id_calon_dpr": "e9d3b85bd9a1658a8c12d453cad288e10806500c74bcc8c1830fe1458775ff96b6a4f1ca90eb09322516987c9b575399d92c9e2d1933aa08eac7046d59943585OqIUNBUmUpyztIS7/F5Nq3BxjozfGjOBkuFi+HagfEE=",
      "logo_partai": "berkas-sipol/parpol/profil/gambar_parpol/1656144884_LOGO%20PARTAI%20PERINDO%2010x10%20cm%20(RGB).png",
      "status_publikasi": "Bersedia"
    },
    "id_partai": 18,
    "kode_dapil": "190504"
  },
  {
    "nomor_urut": 7,
    "foto": "https://infopemilu.kpu.go.id/dct/berkas-silon/calon/85967/pas_foto/1691390733_d93eaab3-a253-4e0b-b98d-1617b8ba1bdc.jpeg",
    "nama": "SANTO KUSUMA ATMAJA, S.E.",
    "jenis_kelamin": "L",
    "alamat_kabko": "BANGKA BARAT",
    "profile": {
      "id_calon_dpr": "cac27bf88635e5f5bc2ac1a59fbd586fe10cca0a28507b478d9d27b48dc5ec16fa4857db5547eab8dbc0786129bcc8c804608506629a49c1a45dca4708a799bbvJuS8VPlM1VRuPCZ9aIozsQ/ZzeUhbIFgOlXTAZ5W3I=",
      "logo_partai": "berkas-sipol/parpol/profil/gambar_parpol/1656144884_LOGO%20PARTAI%20PERINDO%2010x10%20cm%20(RGB).png",
      "status_publikasi": "Bersedia"
    },
    "id_partai": 18,
    "kode_dapil": "190504"
  },
  {
    "nomor_urut": 8,
    "foto": "https://infopemilu.kpu.go.id/dct/berkas-silon/calon/428919/pas_foto/1688833988_987160cf-35a4-467d-bba0-198ba30987be.jpeg",
    "nama": "SUMIATI LAUREN",
    "jenis_kelamin": "P",
    "alamat_kabko": "BANGKA BARAT",
    "profile": {
      "id_calon_dpr": "9761187f3f3af3af03f4d635c9f5ddf05c5083feef222a494646d801f7e647206cc04ea102f263b880267f87c696803e5e27a8fe9f1c31fc08fd20e7d5149a683dskYHDFQbcb/2LrPGGNZLbvIF1TgL6DI6fHsbIkgqA=",
      "logo_partai": "berkas-sipol/parpol/profil/gambar_parpol/1656144884_LOGO%20PARTAI%20PERINDO%2010x10%20cm%20(RGB).png",
      "status_publikasi": "Bersedia"
    },
    "id_partai": 18,
    "kode_dapil": "190504"
  },
  {
    "nomor_urut": 9,
    "foto": "https://infopemilu.kpu.go.id/dct/berkas-silon/calon/84675/pas_foto/1691422318_a139c9bb-3f83-46ab-9252-44b496c5cdd0.jpeg",
    "nama": "ZULKARNAIN",
    "jenis_kelamin": "L",
    "alamat_kabko": "BANGKA BARAT",
    "profile": {
      "id_calon_dpr": "dc9052eb7c43080293b787708aa21b1255b1710785eb5b4138c951bbaedffcd23cc482c53db6b1a464ac2376d7a44fe143b6887fc95f076f0adb3fa67c0d22b9oIRwjpZyealnNZr5TMk7ia0qCSPCGQPfq3mpTRWDfSQ=",
      "logo_partai": "berkas-sipol/parpol/profil/gambar_parpol/1656144884_LOGO%20PARTAI%20PERINDO%2010x10%20cm%20(RGB).png",
      "status_publikasi": "Bersedia"
    },
    "id_partai": 18,
    "kode_dapil": "190504"
  },
  {
    "nomor_urut": 1,
    "foto": "https://infopemilu.kpu.go.id/dct/berkas-silon/calon/88865/pas_foto/1688450448_6d651941-4f1a-4c25-a484-e745adaadfe3.jpeg",
    "nama": "RUDI HARTONO",
    "jenis_kelamin": "L",
    "alamat_kabko": "BANGKA BARAT",
    "profile": {
      "id_calon_dpr": "c053ebfaf95c847799b8879c96e2c18cda4f3b7397543870210ccf03afabe383923c701f8fa60d30dad7390697918006ed9311ee85874f70436a96c3f1dd0e03VmMLpR2cjBdNo01LcgK4kzdcVCebDqobhu/3O/jZLM0=",
      "logo_partai": "berkas-sipol/parpol/profil/gambar_parpol/1658455987_Logo%20PPP.png",
      "status_publikasi": "Bersedia"
    },
    "id_partai": 11,
    "kode_dapil": "190504"
  },
  {
    "nomor_urut": 2,
    "foto": "https://infopemilu.kpu.go.id/dct/berkas-silon/calon/196930/pas_foto/1688450307_b49e0bf7-4441-4033-b0f2-4d8f9e035dcb.jpeg",
    "nama": "MUHAMAD ARIDAFA AMRULLAH",
    "jenis_kelamin": "L",
    "alamat_kabko": "BANGKA BARAT",
    "profile": {
      "id_calon_dpr": "481e008202f9a2f868c8991c77abad5a3e72a8a4ead9b919177f19ad7b8f2cdcc3bafd04e21238b9dc5290fcc860bdbbd78b7c9f1408209d21216ce3a403976c/PTtviUIdvMQL4m0CQUkCFJWkcDPrymDpU+Esvl/L3Y=",
      "logo_partai": "berkas-sipol/parpol/profil/gambar_parpol/1658455987_Logo%20PPP.png",
      "status_publikasi": "Bersedia"
    },
    "id_partai": 11,
    "kode_dapil": "190504"
  },
  {
    "nomor_urut": 3,
    "foto": "https://infopemilu.kpu.go.id/dct/berkas-silon/calon/298144/pas_foto/1688450173_17800743-df3c-4635-b0ec-25c608266b89.jpeg",
    "nama": "RAHMASARITA",
    "jenis_kelamin": "P",
    "alamat_kabko": "BANGKA BARAT",
    "profile": {
      "id_calon_dpr": "c0ad9d184c5dd7cbc685fe36e068b5fc0620a47ee9d9419f1e9d535607ec822279361fd2972a5e63780ce189b05ecaea531ed80d2f06aded93e70bcb9416209fSLvWimzami1p/FfOHr2Aua2fbRPV2jmsD0xOG82Ydvw=",
      "logo_partai": "berkas-sipol/parpol/profil/gambar_parpol/1658455987_Logo%20PPP.png",
      "status_publikasi": "Bersedia"
    },
    "id_partai": 11,
    "kode_dapil": "190504"
  },
  {
    "nomor_urut": 4,
    "foto": "https://infopemilu.kpu.go.id/dct/berkas-silon/calon/241591/pas_foto/1688450049_d33ea5b3-7055-4014-b1e7-6691b1b788e4.jpeg",
    "nama": "AKHMAD ROBIL",
    "jenis_kelamin": "L",
    "alamat_kabko": "BANGKA BARAT",
    "profile": {
      "id_calon_dpr": "cbcd1dd9ad330cbe18ef7bb3aa3607fcf59ccce04228446ed08e4f58206571dd5514d820bf217bceaa33ea2a33288f975fc003632558bd3f9e913e81d808853aM/Mr3ShfDelUdw9X5pxG4beMKInIdRn/sAm0ZRPEtiw=",
      "logo_partai": "berkas-sipol/parpol/profil/gambar_parpol/1658455987_Logo%20PPP.png",
      "status_publikasi": "Bersedia"
    },
    "id_partai": 11,
    "kode_dapil": "190504"
  },
  {
    "nomor_urut": 5,
    "foto": "https://infopemilu.kpu.go.id/dct/berkas-silon/calon/57978/pas_foto/1688449462_5b8fc47b-7220-4c2a-a011-79a83cbe491c.jpeg",
    "nama": "KHOIRUSSOLEH, S.E.",
    "jenis_kelamin": "L",
    "alamat_kabko": "BANGKA BARAT",
    "profile": {
      "id_calon_dpr": "2c71aa533f11c0bb1117571fb146fccc8481a802db2600faa2e6a53ae8b8403a67df4f2a739710ef569f97cfce8054399295ff06ca4d3d373a81bf9b1d03149daHt29AVdHXGmyISVwKnzgSq0bEyo+8flEE94krDO9qY=",
      "logo_partai": "berkas-sipol/parpol/profil/gambar_parpol/1658455987_Logo%20PPP.png",
      "status_publikasi": "Bersedia"
    },
    "id_partai": 11,
    "kode_dapil": "190504"
  },
  {
    "nomor_urut": 6,
    "foto": "https://infopemilu.kpu.go.id/dct/berkas-silon/calon/299341/pas_foto/1688449650_7f5a7569-b917-40d1-84aa-6da4e79eddfe.jpeg",
    "nama": "MESIANA",
    "jenis_kelamin": "P",
    "alamat_kabko": "BANGKA BARAT",
    "profile": {
      "id_calon_dpr": "eb99faae245c633539163e6c371978f40d9ad40016eaa14adbcd1a136702dae3c7b18c7c979296eff21ae125226724c4694b727e224a68603b27226e2402d8d6ratMLgtHnbf6ro4Gjug5jjKT/YH8g8Ea0o4abF2UQ1o=",
      "logo_partai": "berkas-sipol/parpol/profil/gambar_parpol/1658455987_Logo%20PPP.png",
      "status_publikasi": "Bersedia"
    },
    "id_partai": 11,
    "kode_dapil": "190504"
  },
  {
    "nomor_urut": 7,
    "foto": "https://infopemilu.kpu.go.id/dct/berkas-silon/calon/196623/pas_foto/1688449757_6cdfcc31-5490-46b7-bc83-3550108f9c35.jpeg",
    "nama": "ARIFIN",
    "jenis_kelamin": "L",
    "alamat_kabko": "BANGKA BARAT",
    "profile": {
      "id_calon_dpr": "027893e75a002bacda8e02d27aab3fd25ac1a45f8cd571e86f2b5e53931d03ad03f1a688abb301dee3f78f6b67520c1307563827e18f0bc7721d9aabb86eb6e0AJan9J4UBFCuht/P/UvxDaJVZCPGQzvhgUx/DEnrXas=",
      "logo_partai": "berkas-sipol/parpol/profil/gambar_parpol/1658455987_Logo%20PPP.png",
      "status_publikasi": "Bersedia"
    },
    "id_partai": 11,
    "kode_dapil": "190504"
  },
  {
    "nomor_urut": 8,
    "foto": "https://infopemilu.kpu.go.id/dct/berkas-silon/calon/299964/pas_foto/1688449903_3c6a84b7-b960-471c-a084-6f4231f82344.jpeg",
    "nama": "SARTIKA",
    "jenis_kelamin": "P",
    "alamat_kabko": "BANGKA BARAT",
    "profile": {
      "id_calon_dpr": "30394b3f96401fd0f7a6f2031aa48bed874654877f14e62794d40a8b2bfd5bfc7972bfd1645b22da4337f975b2432f156b14c0a27e3391d325aa9d40a0e6c6a9IXFq6GZ5d0aJ8dZoAdAQrZFhigDG2YkX08mqmqUEzd0=",
      "logo_partai": "berkas-sipol/parpol/profil/gambar_parpol/1658455987_Logo%20PPP.png",
      "status_publikasi": "Bersedia"
    },
    "id_partai": 11,
    "kode_dapil": "190504"
  },
  {
    "nomor_urut": 9,
    "foto": "https://infopemilu.kpu.go.id/dct/berkas-silon/calon/300719/pas_foto/1688568201_5de7069e-ff32-443a-821b-1a9cbca3cbe5.jpeg",
    "nama": "JONIZAR",
    "jenis_kelamin": "L",
    "alamat_kabko": "BANGKA BARAT",
    "profile": {
      "id_calon_dpr": "a7cba755c4f748bc8e31d54a9eb5c8b291d1516e10593e2fa266df475379abf93f309ec38403cbfaebe79fd0884afaab041b3cebd31d1ba1ea3c98982600e169TR8w2fSrpHlfkruAbQHwj3wnGQNiTn+uqmEDg7oi0JY=",
      "logo_partai": "berkas-sipol/parpol/profil/gambar_parpol/1658455987_Logo%20PPP.png",
      "status_publikasi": "Bersedia"
    },
    "id_partai": 11,
    "kode_dapil": "190504"
  },
  {
    "nomor_urut": 1,
    "foto": "https://infopemilu.kpu.go.id/dct/berkas-silon/calon/149885/pas_foto/1683530942_0fefe10d-3b81-4aee-b43a-ae626bba3e7b.jpeg",
    "nama": "LATIF",
    "jenis_kelamin": "L",
    "alamat_kabko": "BANGKA BARAT",
    "profile": {
      "id_calon_dpr": "4e2bdb35d003ebce32aa9fe133510f981c9e4560dfaa7fdd0b0d6bc03b37ab017cdb8c45e6801e349a16613901e2368e802a2db882160ae0086dab79bce48ff4b6zyLMNjGhiIvSivlRaV3BOZWv4s/Gwdac/NdiIXADk=",
      "logo_partai": "berkas-sipol/parpol/profil/gambar_parpol/1656157120_LOGO%20PARTAI%20UMMAT%2010X10%20CM%20KPU.png",
      "status_publikasi": "Bersedia"
    },
    "id_partai": 78,
    "kode_dapil": "190504"
  },
  {
    "nomor_urut": 2,
    "foto": "https://infopemilu.kpu.go.id/dct/berkas-silon/calon/150087/pas_foto/1683531110_2c4a2552-d34b-465e-88a0-e5c072cd1f8d.jpeg",
    "nama": "RANDA",
    "jenis_kelamin": "L",
    "alamat_kabko": "BANGKA BARAT",
    "profile": {
      "id_calon_dpr": "e323d33310bb7a7d5abbc29142e32121b2885d72d60318c31a2681042d48ad63b79bbd50a8a77269a6eca31ebf07e904c4877c6268fc8b182081976f6d84187bTg0f7I6Cse3ERYjMK64JGLN05oKOYJBdgURXJTn4KPs=",
      "logo_partai": "berkas-sipol/parpol/profil/gambar_parpol/1656157120_LOGO%20PARTAI%20UMMAT%2010X10%20CM%20KPU.png",
      "status_publikasi": "Bersedia"
    },
    "id_partai": 78,
    "kode_dapil": "190504"
  },
  {
    "nomor_urut": 3,
    "foto": "https://infopemilu.kpu.go.id/dct/berkas-silon/calon/150311/pas_foto/1683531562_6961927a-4185-4dce-8b83-af97d1ac6309.jpeg",
    "nama": "AZIZAH",
    "jenis_kelamin": "P",
    "alamat_kabko": "BANGKA BARAT",
    "profile": {
      "id_calon_dpr": "800aff3d699dad0f23d5f9a748ef99bc43f014ef41580a787752908dd74cf924cdfc27dc999a3330bbbac11fec184fa927de9cf0dd3676d35e73e5bd200a3a95MiaKHLWY9luH/+cYVlnFF6mp+/zJYyUQwTlQ2N/dbvg=",
      "logo_partai": "berkas-sipol/parpol/profil/gambar_parpol/1656157120_LOGO%20PARTAI%20UMMAT%2010X10%20CM%20KPU.png",
      "status_publikasi": "Bersedia"
    },
    "id_partai": 78,
    "kode_dapil": "190504"
  },
  {
    "nomor_urut": 4,
    "foto": "https://infopemilu.kpu.go.id/dct/berkas-silon/calon/150166/pas_foto/1683531421_ae1369fd-a9cd-47a1-a794-3aee45df54e9.jpeg",
    "nama": "YUDI HARDIANSYAH",
    "jenis_kelamin": "L",
    "alamat_kabko": "BANGKA BARAT",
    "profile": {
      "id_calon_dpr": "358fc35c38aa6f3ce43d0ea08d39c1a732f64fe2974fa247bc91e5141642683b9e272df3fa6f8765fe000450bb596f3bec79ddceecfe5679d8075df86826386eKMS4Jhmlqd+x4AKbQq2pYHz2XztYwDTogNCIpgcRgRg=",
      "logo_partai": "berkas-sipol/parpol/profil/gambar_parpol/1656157120_LOGO%20PARTAI%20UMMAT%2010X10%20CM%20KPU.png",
      "status_publikasi": "Bersedia"
    },
    "id_partai": 78,
    "kode_dapil": "190504"
  },
  {
    "nomor_urut": 5,
    "foto": "https://infopemilu.kpu.go.id/dct/berkas-silon/calon/185013/pas_foto/1683633181_941650b2-28da-4412-adff-3727153850fe.jpeg",
    "nama": "ANGGREY",
    "jenis_kelamin": "L",
    "alamat_kabko": "BANGKA BARAT",
    "profile": {
      "id_calon_dpr": "e768c29668af9e5bcdfb1232bed2da7b9be08b1c4a9741371d3b62372d6614856a4b7b06fe71a30f68347b69c3da8bed9552faaaa8388e01265bd8ffaea404670Mxfub6x8pblX3CGeCugspkb54rOvEXs9km2h1+PljM=",
      "logo_partai": "berkas-sipol/parpol/profil/gambar_parpol/1656157120_LOGO%20PARTAI%20UMMAT%2010X10%20CM%20KPU.png",
      "status_publikasi": "Bersedia"
    },
    "id_partai": 78,
    "kode_dapil": "190504"
  },
  {
    "nomor_urut": 6,
    "foto": "https://infopemilu.kpu.go.id/dct/berkas-silon/calon/184475/pas_foto/1683632145_6e22d2bb-9cf2-44f9-ad4d-17efff3a6e87.jpeg",
    "nama": "KESI",
    "jenis_kelamin": "P",
    "alamat_kabko": "BANGKA BARAT",
    "profile": {
      "id_calon_dpr": "656e40f5239186871b6b26bab10cfed55f6d44678cfb15ce6d91321277a2449b9833d3362d7ed07745f7619b6ceedcea9c548b3da471177859546e1b283db18a5HruSDQeMpnHwjnnpRBbXgf+YB6JTkCb2zDZlFHXoHk=",
      "logo_partai": "berkas-sipol/parpol/profil/gambar_parpol/1656157120_LOGO%20PARTAI%20UMMAT%2010X10%20CM%20KPU.png",
      "status_publikasi": "Bersedia"
    },
    "id_partai": 78,
    "kode_dapil": "190504"
  },
  {
    "nomor_urut": 7,
    "foto": "https://infopemilu.kpu.go.id/dct/berkas-silon/calon/429732/pas_foto/1688505358_4f277f83-7d35-4500-a177-d028f8c72ef8.jpeg",
    "nama": "FITRIYANI",
    "jenis_kelamin": "P",
    "alamat_kabko": "BANGKA BARAT",
    "profile": {
      "id_calon_dpr": "418918e9224c2098e8b65d07393eaad25c0b27c15bbd6d955c197ad5c9271dc09542616d0fa339d1644d9532438fb4cb0abb10a6ca9b3924d3a9e726c0aad218qCGYpm8Cn6YQ1cfEXxNd6Q3cVPjYwFznPtcFrZguoAE=",
      "logo_partai": "berkas-sipol/parpol/profil/gambar_parpol/1656157120_LOGO%20PARTAI%20UMMAT%2010X10%20CM%20KPU.png",
      "status_publikasi": "Bersedia"
    },
    "id_partai": 78,
    "kode_dapil": "190504"
  },
  {
    "nomor_urut": 8,
    "foto": "https://infopemilu.kpu.go.id/dct/berkas-silon/calon/263793/pas_foto/1683781718_0b5df2ad-eadb-457d-94a7-1150fde285b4.jpeg",
    "nama": "MANDIRI ARIF SUJOYO",
    "jenis_kelamin": "L",
    "alamat_kabko": "BANGKA BARAT",
    "profile": {
      "id_calon_dpr": "f3192afe1f9c6d81efcf5aa40eab39567f42278d9914c271d4b1d13bf33a9795684aa5cc7ecf724b3cea5616595e4f3fdf3fd0083be643bf5683549f1fa5caa8//zX9hbUy1lRDwbEYDFtVAkNYjyfNtshxDGPTFJ8ILI=",
      "logo_partai": "berkas-sipol/parpol/profil/gambar_parpol/1656157120_LOGO%20PARTAI%20UMMAT%2010X10%20CM%20KPU.png",
      "status_publikasi": "Bersedia"
    },
    "id_partai": 78,
    "kode_dapil": "190504"
  }
]