[
  {
    "id": 350201,
    "name": " SLAHUNG"
  },
  {
    "id": 350202,
    "name": " NGRAYUN"
  },
  {
    "id": 350203,
    "name": " BUNGKAL"
  },
  {
    "id": 350204,
    "name": " SAMBIT"
  },
  {
    "id": 350205,
    "name": " SAWOO"
  },
  {
    "id": 350206,
    "name": " SOOKO"
  },
  {
    "id": 350207,
    "name": " PULUNG"
  },
  {
    "id": 350208,
    "name": " MLARAK"
  },
  {
    "id": 350209,
    "name": " JETIS"
  },
  {
    "id": 350210,
    "name": " SIMAN"
  },
  {
    "id": 350211,
    "name": " BALONG"
  },
  {
    "id": 350212,
    "name": " KAUMAN"
  },
  {
    "id": 350213,
    "name": " BADEGAN"
  },
  {
    "id": 350214,
    "name": " SAMPUNG"
  },
  {
    "id": 350215,
    "name": " SUKOREJO"
  },
  {
    "id": 350216,
    "name": " BABADAN"
  },
  {
    "id": 350217,
    "name": " PONOROGO"
  },
  {
    "id": 350218,
    "name": " JENANGAN"
  },
  {
    "id": 350219,
    "name": " NGEBEL"
  },
  {
    "id": 350220,
    "name": " JAMBON"
  },
  {
    "id": 350221,
    "name": " PUDAK"
  }
]