[
  {
    "id": 810101,
    "name": " AMAHAI"
  },
  {
    "id": 810102,
    "name": " TEON NILA SERUA"
  },
  {
    "id": 810106,
    "name": " SERAM UTARA"
  },
  {
    "id": 810109,
    "name": " BANDA"
  },
  {
    "id": 810111,
    "name": " TEHORU"
  },
  {
    "id": 810112,
    "name": " SAPARUA"
  },
  {
    "id": 810113,
    "name": " PULAU HARUKU"
  },
  {
    "id": 810114,
    "name": " SALAHUTU"
  },
  {
    "id": 810115,
    "name": " LEIHITU"
  },
  {
    "id": 810116,
    "name": " NUSA LAUT"
  },
  {
    "id": 810117,
    "name": " KOTA MASOHI"
  },
  {
    "id": 810120,
    "name": " SERAM UTARA BARAT"
  },
  {
    "id": 810121,
    "name": " TELUK ELPAPUTIH"
  },
  {
    "id": 810122,
    "name": " LEIHITU BARAT"
  },
  {
    "id": 810123,
    "name": " TELUTIH"
  },
  {
    "id": 810124,
    "name": " SERAM UTARA TIMUR SETI"
  },
  {
    "id": 810125,
    "name": " SERAM UTARA TIMUR KOBI"
  },
  {
    "id": 810126,
    "name": " SAPARUA TIMUR"
  }
]