[
  {
    "nomor_urut": 1,
    "foto": "https://i.ibb.co/2hmp2Ck/18-1.jpg",
    "nama": "KH. Ir. ABDUL HAKIM, M.M.",
    "jenis_kelamin": "L",
    "alamat_kabko": "KOTA JAKARTA SELATAN / DKI JAKARTA",
    "profile": {
      "ID_CANDIDATE": "556aba48aab3e45dd9a146f74a68c7c5677b150e60a5c974b223032e28da2d616cd44676b13632956f97fc882331e9ead01325184c996d89f5414610f227908eX6O4FExsDbEpA96PIegXHtxwtxl7X2oqVdhE490pEkY=",
      "pilihan_publikasi": "BERSEDIA"
    },
    "kode_propinsi": "18"
  },
  {
    "nomor_urut": 2,
    "foto": "https://i.ibb.co/VtsLS8N/18-2.jpg",
    "nama": "AGUNG IMAM PRASETYO",
    "jenis_kelamin": "L",
    "alamat_kabko": "KAB. LAMPUNG BARAT / LAMPUNG",
    "profile": {
      "ID_CANDIDATE": "99781191175871b30b418c79bc2afebe7d183ea7e5c174b82a0365d3c735ef6f8c56c9c7a95ef1628fe7b6da06f0fd300de485f67dcf94712c2de19dcbf94847SE/igmnscyYx4AVZckkIOxD7E03edd+sDuJnUoKYxUU=",
      "pilihan_publikasi": "BERSEDIA"
    },
    "kode_propinsi": "18"
  },
  {
    "nomor_urut": 3,
    "foto": "https://i.ibb.co/DQhP13y/18-3.jpg",
    "nama": "Drs. H. AHMAD BASTIAN SY",
    "jenis_kelamin": "L",
    "alamat_kabko": "KOTA BANDAR LAMPUNG / LAMPUNG",
    "profile": {
      "ID_CANDIDATE": "d4f2d8da1e2e5477e048ae450944110761da2edf8d1c803cf38232aa1a03360e30ee2319c66d3b40801b81c8b7f3c7db0a30ace44955a33489f6938905b234c2gMSrEmk5fIrRU02FCovdOPuiGdvFakWvsu9BwWLb+4o=",
      "pilihan_publikasi": "BERSEDIA"
    },
    "kode_propinsi": "18"
  },
  {
    "nomor_urut": 4,
    "foto": "https://i.ibb.co/F6v6CbX/18-4.jpg",
    "nama": "ALMIRA NABILA FAUZI, B.Bus. Com.",
    "jenis_kelamin": "P",
    "alamat_kabko": "KAB. PRINGSEWU / LAMPUNG",
    "profile": {},
    "kode_propinsi": "18"
  },
  {
    "nomor_urut": 5,
    "foto": "https://i.ibb.co/CKjNvr5/18-5.jpg",
    "nama": "H. BENNY UZER, S.H.",
    "jenis_kelamin": "L",
    "alamat_kabko": "KOTA BANDAR LAMPUNG / LAMPUNG",
    "profile": {},
    "kode_propinsi": "18"
  },
  {
    "nomor_urut": 6,
    "foto": "https://i.ibb.co/3z3YHsd/18-6.jpg",
    "nama": "Dr. H. BUSTAMI ZAINUDIN, S.Pd, M.H.",
    "jenis_kelamin": "L",
    "alamat_kabko": "KAB. WAY KANAN / LAMPUNG",
    "profile": {
      "ID_CANDIDATE": "1b1bc39158085960dcb534dde697a9cd2b8122d3fb33353c3176d683f550557ed63f85867837b76ce8508ea4570a3871f58c8c9e10a309643f9f88c96f5149dc+ymHFFAfJdh8AB43rdYkiVNevKH+df0LqyEcCQxRVW0=",
      "pilihan_publikasi": "BERSEDIA"
    },
    "kode_propinsi": "18"
  },
  {
    "nomor_urut": 7,
    "foto": "https://i.ibb.co/GpcsN52/18-7.jpg",
    "nama": "DAVIT KURNIAWAN, S. Kom.",
    "jenis_kelamin": "L",
    "alamat_kabko": "KOTA BANDAR LAMPUNG / LAMPUNG",
    "profile": {
      "ID_CANDIDATE": "751a27d8bea1a08fad2c65d29fad66e50df8a428076ae0c55b64888c6b1570963fea0aed6a0380634a4d2e4b026c3ea71d6cef9709f836b71195c097272f00b1BATu/wXtBRmoBqvb2s4TnCzugjpCjHqBAsLE4DVbtl0=",
      "pilihan_publikasi": "BERSEDIA"
    },
    "kode_propinsi": "18"
  },
  {
    "nomor_urut": 8,
    "foto": "https://i.ibb.co/fNzXtqK/18-8.jpg",
    "nama": "DEVI SISWANDANI, S.Pd",
    "jenis_kelamin": "P",
    "alamat_kabko": "KAB. LAMPUNG BARAT / LAMPUNG",
    "profile": {},
    "kode_propinsi": "18"
  },
  {
    "nomor_urut": 9,
    "foto": "https://i.ibb.co/b5Rk3sL/18-9.jpg",
    "nama": "DYAH SITI NURAINI, S.E., M.Ak.",
    "jenis_kelamin": "P",
    "alamat_kabko": "KOTA JAKARTA UTARA / DKI JAKARTA",
    "profile": {},
    "kode_propinsi": "18"
  },
  {
    "nomor_urut": 10,
    "foto": "https://i.ibb.co/9YLL6Qc/18-10.jpg",
    "nama": "FARAH NURIZA AMELIA, S.H.",
    "jenis_kelamin": "P",
    "alamat_kabko": "KOTA JAKARTA SELATAN / DKI JAKARTA",
    "profile": {},
    "kode_propinsi": "18"
  },
  {
    "nomor_urut": 11,
    "foto": "https://i.ibb.co/TLpCYwN/18-11.jpg",
    "nama": "HERI PROLETARI DWI KARTIKA.AZ",
    "jenis_kelamin": "L",
    "alamat_kabko": "KAB. PRINGSEWU / LAMPUNG",
    "profile": {
      "ID_CANDIDATE": "480d967478d26b958ddf255d15dc53d877c647ad2f1011187e4617c21c4e313aee2079feb17a83aff32a76a9e3674e328b045c1fa6ab554f0e413fc8327c5c5an86KBFPgdQXMTOMsRrJuctfCfHq+eVzl9t3uzxKQJBM=",
      "pilihan_publikasi": "BERSEDIA"
    },
    "kode_propinsi": "18"
  },
  {
    "nomor_urut": 12,
    "foto": "https://i.ibb.co/fq94pF0/18-12.jpg",
    "nama": "dr. JIHAN NURLELA, M.M.",
    "jenis_kelamin": "P",
    "alamat_kabko": "KOTA BANDAR LAMPUNG / LAMPUNG",
    "profile": {},
    "kode_propinsi": "18"
  },
  {
    "nomor_urut": 13,
    "foto": "https://i.ibb.co/VCkTrvb/18-13.jpg",
    "nama": "H. KHAIDIR BUJUNG, S.Ag., M.M.",
    "jenis_kelamin": "L",
    "alamat_kabko": "KOTA BANDAR LAMPUNG / LAMPUNG",
    "profile": {
      "ID_CANDIDATE": "022374553f6ee91ee7f682a9366300f95da2f3a0fd8e0bc25c99d2e367ae258fd70ebe6dcaa82f4f58afd8a7dae0a5c8b7a0c36f67a5bbf37982bb93fb5607641pExNuvOwhQcuChIR4sfEPgwOJ4ibiSoiAvdQXXA8iI=",
      "pilihan_publikasi": "BERSEDIA"
    },
    "kode_propinsi": "18"
  },
  {
    "nomor_urut": 14,
    "foto": "https://i.ibb.co/jv73Ygq/18-14.jpg",
    "nama": "PETRUS TJANDRA",
    "jenis_kelamin": "L",
    "alamat_kabko": "KOTA JAKARTA BARAT / DKI JAKARTA",
    "profile": {},
    "kode_propinsi": "18"
  },
  {
    "nomor_urut": 15,
    "foto": "https://i.ibb.co/tQWrTNg/18-15.jpg",
    "nama": "H. SM HERLAMBANG, S.H., M.H",
    "jenis_kelamin": "L",
    "alamat_kabko": "KAB. LAMPUNG TENGAH / LAMPUNG",
    "profile": {},
    "kode_propinsi": "18"
  },
  {
    "nomor_urut": 16,
    "foto": "https://i.ibb.co/dDbgpFJ/18-16.jpg",
    "nama": "H. SUPENO, S.H.I.",
    "jenis_kelamin": "L",
    "alamat_kabko": "KAB. TULANG BAWANG BARAT / LAMPUNG",
    "profile": {
      "ID_CANDIDATE": "dc4ace1a5fa3b5ad86bf59553f409b57a784663c507e11a22c151adfa348e78cf8676ca5d08ee5371a18486984d5baf4e5460e80f942474b774e98b021e49de5hcx+lDcLQzd4QWnUz2NikfbraMNoSgQzbU1C9wMf4dE=",
      "pilihan_publikasi": "BERSEDIA"
    },
    "kode_propinsi": "18"
  },
  {
    "nomor_urut": 17,
    "foto": "https://i.ibb.co/b6xCryt/18-17.jpg",
    "nama": "H. TULUS PURNOMO WIBOWO",
    "jenis_kelamin": "L",
    "alamat_kabko": "KAB. LAMPUNG SELATAN / LAMPUNG",
    "profile": {},
    "kode_propinsi": "18"
  }
]